{
"skeleton": {
	"hash": "UIQt1cWnarOY+RHVZ7scluuGzic",
	"spine": "3.8.99",
	"x": -227.68,
	"y": -12.96,
	"width": 483.26,
	"height": 742.52,
	"images": "./images/",
	"audio": ""
},
"bones": [
	{ "name": "root" },
	{ "name": "shadow", "parent": "root" },
	{ "name": "Zy", "parent": "root", "color": "f44fffff" },
	{ "name": "Body", "parent": "root", "y": 65.46 },
	{ "name": "Body2", "parent": "Body", "length": 66.17, "rotation": 88.97, "x": -0.47, "y": -0.06 },
	{ "name": "Rh", "parent": "Body2", "rotation": -177.62, "x": 81.42, "y": 81.85, "scaleX": -1 },
	{ "name": "Rh_1", "parent": "Rh", "length": 57.13, "rotation": -108.1, "x": -0.84, "y": -2.21 },
	{ "name": "Rh_2", "parent": "Rh_1", "length": 62.81, "rotation": -48.38, "x": 57.13 },
	{ "name": "Rh_3", "parent": "Rh_2", "length": 32.57, "rotation": 13.94, "x": 62.81 },
	{ "name": "Gj", "parent": "Rh_3", "rotation": 126.11, "x": -37.94, "y": -171.12, "color": "f44fffff" },
	{ "name": "Tx", "parent": "root", "color": "f44fffff" },
	{ "name": "Head", "parent": "Body2", "length": 65.64, "rotation": 5.4, "x": 66.17 },
	{ "name": "Hat", "parent": "Head", "x": 117.98, "y": 27.65 },
	{ "name": "Hat1", "parent": "Hat", "length": 139.49, "rotation": -6.96, "x": 33.35, "y": -38.91 },
	{ "name": "Hat2", "parent": "Hat1", "length": 133.93, "rotation": 0.97, "x": 139.49 },
	{ "name": "Hat3", "parent": "Hat2", "length": 112.09, "rotation": -0.45, "x": 133.93 },
	{ "name": "Lh", "parent": "Body2", "x": 84.64, "y": -88.66 },
	{ "name": "Lh_1", "parent": "Lh", "length": 57.13, "rotation": -108.1, "x": -0.84, "y": -2.21 },
	{ "name": "Lh_2", "parent": "Lh_1", "length": 62.81, "rotation": -48.38, "x": 57.13 },
	{ "name": "Lh_qt", "parent": "Lh_2", "length": 32.57, "rotation": 13.94, "x": 62.81 },
	{ "name": "Lf_1", "parent": "Body", "length": 31.77, "rotation": -83.13, "x": 66.17, "y": 2.38 },
	{ "name": "Lf_2", "parent": "Lf_1", "length": 28.75, "rotation": -3.08, "x": 31.77 },
	{ "name": "Lf_3", "parent": "Lf_2", "length": 19.97, "rotation": 60.86, "x": 28.75 },
	{ "name": "hz1", "parent": "Head", "length": 41.86, "rotation": -117.98, "x": 48.3, "y": 32.34 },
	{ "name": "hz2", "parent": "hz1", "length": 41.41, "rotation": 22.56, "x": 41.86 },
	{ "name": "hz3", "parent": "hz2", "length": 46.24, "rotation": 26.77, "x": 41.41 },
	{ "name": "hz4", "parent": "Head", "length": 33.17, "rotation": 112.98, "x": 50.54, "y": 55.1 },
	{ "name": "hz5", "parent": "hz4", "length": 35.75, "rotation": -36.34, "x": 33.17 },
	{ "name": "hz6", "parent": "hz5", "length": 36.58, "rotation": -26.68, "x": 35.75 },
	{ "name": "L_E", "parent": "Head", "x": 100.62, "y": -29.23 },
	{ "name": "jh", "parent": "Hat1", "x": 70.05, "y": 49 },
	{
		"name": "Body7",
		"parent": "Body2",
		"length": 59.82,
		"rotation": -164.93,
		"x": 71.27,
		"y": -72.25,
		"color": "ff5757ff"
	},
	{ "name": "Body8", "parent": "Body7", "length": 59.91, "rotation": 5.62, "x": 59.82, "color": "ff5757ff" },
	{ "name": "L_Qt", "parent": "Body8", "rotation": 159.32, "x": 17.72, "y": 6.82 },
	{ "name": "Hat4", "parent": "Hat", "length": 86.94, "rotation": 54.51, "x": 8.49, "y": 17.38 },
	{ "name": "Hat5", "parent": "Hat4", "length": 112.1, "rotation": -21.59, "x": 86.94 },
	{ "name": "Hat6", "parent": "Hat", "length": 91.01, "rotation": -80.85, "x": 2.47, "y": -29.98 },
	{ "name": "Hat7", "parent": "Hat6", "length": 91.65, "rotation": 15.35, "x": 91.01 },
	{ "name": "Hat8", "parent": "Hat7", "length": 85.89, "rotation": 14.51, "x": 91.65 },
	{ "name": "Hat9", "parent": "Hat3", "length": 32.87, "rotation": 64.2, "x": 131.15, "y": 14.78 },
	{ "name": "Hat10", "parent": "Hat3", "length": 33.81, "rotation": -67.71, "x": 130.06, "y": 7.72 },
	{ "name": "headctrl", "parent": "Head", "rotation": -94.37, "x": 49, "y": 42.62, "color": "abe323ff" },
	{
		"name": "Body9",
		"parent": "Body2",
		"length": 56.71,
		"rotation": 172.04,
		"x": 69.83,
		"y": 75.25,
		"color": "ff5757ff"
	},
	{ "name": "Body10", "parent": "Body9", "length": 59.24, "rotation": -4.38, "x": 56.71, "color": "ff5757ff" },
	{ "name": "R_Qt", "parent": "Body10", "rotation": -167.66, "x": 16.03, "y": -6.28 },
	{
		"name": "Lf_4",
		"parent": "Body",
		"length": 31.77,
		"rotation": 86.19,
		"x": -51.01,
		"y": 2.38,
		"scaleX": -1
	},
	{ "name": "Lf_5", "parent": "Lf_4", "length": 28.75, "rotation": -3.08, "x": 31.77 },
	{ "name": "Lf_6", "parent": "Lf_5", "length": 19.97, "rotation": 60.86, "x": 28.75 },
	{ "name": "Lf_ctrl", "parent": "root", "x": 71.2, "y": 7.71, "color": "ff3f00ff" },
	{ "name": "Rf_ctrl", "parent": "root", "x": -56.51, "y": 7.87, "color": "ff3f00ff" },
	{ "name": "Lh_qt2", "parent": "Lh_qt", "length": 17.28, "rotation": -0.01, "x": 34.07, "y": 0.2 },
	{ "name": "Lh_qt3", "parent": "Lh_qt2", "length": 14.59, "rotation": -37.01, "x": 17.36, "y": -0.15 },
	{ "name": "Lh_qt4", "parent": "Lh_qt", "length": 17.5, "rotation": -75.79, "x": 6.78, "y": -20.65 },
	{ "name": "Lh_qt5", "parent": "Lh_qt4", "length": 13.74, "rotation": 23.63, "x": 17.92, "y": -0.04 },
	{ "name": "Rh_qt2", "parent": "Rh_3", "length": 17.28, "rotation": -0.01, "x": 34.07, "y": 0.2 },
	{ "name": "Rh_qt3", "parent": "Rh_qt2", "length": 14.59, "rotation": -37.01, "x": 17.36, "y": -0.15 },
	{ "name": "Rh_qt4", "parent": "Rh_3", "length": 17.5, "rotation": -75.79, "x": 6.78, "y": -20.65 },
	{ "name": "Rh_qt5", "parent": "Rh_qt4", "length": 13.74, "rotation": 23.63, "x": 17.92, "y": -0.04 },
	{ "name": "wuqi", "parent": "Rh_3", "rotation": -53.68, "x": 32.57, "scaleX": -1 },
	{
		"name": "pukepai",
		"parent": "Rh_3",
		"rotation": -94.49,
		"x": 89.49,
		"y": -10.76,
		"scaleX": 0.4,
		"scaleY": 0.4
	},
	{ "name": "l_wq", "parent": "Lh_qt", "x": 32.57 },
	{
		"name": "Body3",
		"parent": "Body2",
		"length": 69.75,
		"rotation": -66.55,
		"x": 93.79,
		"y": -69.02,
		"color": "ff5757ff"
	},
	{ "name": "Body4", "parent": "Body3", "length": 79.04, "rotation": -16.27, "x": 69.75, "color": "ff5757ff" },
	{
		"name": "Body5",
		"parent": "Body2",
		"length": 53.24,
		"rotation": 61.55,
		"x": 88.93,
		"y": 66.73,
		"color": "ff5757ff"
	},
	{ "name": "Body6", "parent": "Body5", "length": 78.64, "rotation": 27.42, "x": 53.24, "color": "ff5757ff" },
	{
		"name": "Body11",
		"parent": "Body2",
		"length": 50.43,
		"rotation": -112.45,
		"x": 95.42,
		"y": -109.86,
		"color": "ff5757ff"
	},
	{ "name": "Body12", "parent": "Body11", "length": 43.6, "rotation": 6.91, "x": 50.43, "color": "ff5757ff" },
	{
		"name": "Body13",
		"parent": "Body2",
		"length": 49.76,
		"rotation": 113.65,
		"x": 85.94,
		"y": 97.99,
		"color": "ff5757ff"
	},
	{ "name": "Body14", "parent": "Body13", "length": 48.12, "rotation": -4.06, "x": 49.76, "color": "ff5757ff" },
	{ "name": "yanjing", "parent": "Head", "x": 88.26, "y": 92.52 },
	{ "name": "yandou", "parent": "Head", "x": 30.54, "y": 39.91 }
],
"slots": [
	{ "name": "yifuwai2", "bone": "Body2", "attachment": "yifudi" },
	{ "name": "Rh_1", "bone": "Rh_1", "attachment": "Lh_1" },
	{ "name": "Rh_qt1", "bone": "Rh_3", "attachment": "H_L_sz" },
	{ "name": "Rh_qt2", "bone": "Rh_3", "attachment": "H_L_sz1" },
	{ "name": "Rh_2", "bone": "Rh_2", "attachment": "Lh_2" },
	{ "name": "Rf", "bone": "Lf_4", "attachment": "F_L" },
	{ "name": "Lf", "bone": "Lf_1", "attachment": "F_L" },
	{ "name": "Body", "bone": "Body", "attachment": "Body" },
	{ "name": "Lh_1", "bone": "Lh_1", "attachment": "Lh_1" },
	{ "name": "Lh_qt1", "bone": "Lh_qt", "attachment": "H_L_sz" },
	{ "name": "Lh_qt2", "bone": "Lh_qt", "attachment": "H_L_sz1" },
	{ "name": "Lh_2", "bone": "Lh_2", "attachment": "Lh_2" },
	{ "name": "yifuwai7", "bone": "Body2", "attachment": "yifuxiuzi" },
	{ "name": "Wu_R", "bone": "R_Qt", "attachment": "Wu_R" },
	{ "name": "yifuwai", "bone": "Body2", "attachment": "yifuwai" },
	{ "name": "yifuwai4", "bone": "Body2", "attachment": "yifulinzi" },
	{ "name": "Wu_L", "bone": "L_Qt", "attachment": "Wu_L" },
	{ "name": "tou_3", "bone": "Head", "attachment": "tou_di" },
	{ "name": "tou_1", "bone": "Head", "attachment": "tou_1" },
	{ "name": "Hu", "bone": "Head", "attachment": "Hu" },
	{ "name": "glass", "bone": "yanjing", "attachment": "glass" },
	{ "name": "Hat1", "bone": "Hat", "attachment": "Hat1" },
	{ "name": "tou_2", "bone": "Hat", "attachment": "tou_2" },
	{ "name": "Flower", "bone": "Hat3", "attachment": "Flower" },
	{ "name": "hat3", "bone": "Hat", "attachment": "hat3" },
	{ "name": "hat2", "bone": "jh", "attachment": "hat2" },
	{ "name": "yand", "bone": "yandou", "attachment": "yand" }
],
"ik": [
	{
		"name": "Lf_ctrl",
		"bones": [ "Lf_1", "Lf_2" ],
		"target": "Lf_ctrl",
		"bendPositive": false
	},
	{
		"name": "Rf_ctrl",
		"order": 1,
		"bones": [ "Lf_4", "Lf_5" ],
		"target": "Rf_ctrl"
	}
],
"transform": [
	{
		"name": "headctrl1",
		"order": 2,
		"bones": [ "Hat" ],
		"target": "headctrl",
		"rotation": 94.37,
		"x": 9.67,
		"y": 69.92,
		"shearY": -360,
		"rotateMix": 0,
		"translateMix": 0.3,
		"scaleMix": 0,
		"shearMix": 0
	},
	{
		"name": "headctrl2",
		"order": 3,
		"bones": [ "hz4" ],
		"target": "headctrl",
		"rotation": -152.65,
		"x": -12.56,
		"y": 0.59,
		"rotateMix": 0,
		"translateMix": 0.3,
		"scaleMix": 0,
		"shearMix": 0
	},
	{
		"name": "headctrl3",
		"order": 4,
		"bones": [ "hz1" ],
		"target": "headctrl",
		"rotation": -23.61,
		"x": 10.3,
		"y": 0.08,
		"rotateMix": 0,
		"translateMix": 0.3,
		"scaleMix": 0,
		"shearMix": 0
	}
],
"skins": [
	{
		"name": "default",
		"attachments": {
			"Body": {
				"Body": { "x": 6.61, "y": 35.09, "width": 240, "height": 150 }
			},
			"Flower": {
				"Flower": {
					"type": "mesh",
					"uvs": [ 0.00124, 0.1704, 0.20556, 0.01393, 0.42295, 0, 0.64774, 0, 0.85353, 0.09776, 1, 0.29278, 0.99999, 0.60383, 0.82302, 0.95901, 0.62668, 0.99999, 0.34234, 1, 0.06326, 0.94487, 0, 0.53273 ],
					"triangles": [ 8, 3, 7, 8, 2, 3, 7, 4, 6, 7, 3, 4, 6, 4, 5, 9, 11, 1, 9, 2, 8, 9, 1, 2, 9, 10, 11, 1, 11, 0 ],
					"vertices": [ 1, 39, 65.04, -1.67, 1, 2, 39, 46.02, -21.64, 0.97965, 40, -20.75, 52.38, 0.02035, 2, 39, 21.78, -35.34, 0.67955, 40, 5.63, 43.49, 0.32045, 2, 39, -3.65, -48.79, 0.1423, 40, 32.63, 33.54, 0.8577, 2, 39, -29.5, -56.26, 0.00608, 40, 55.45, 19.3, 0.99392, 1, 40, 69.27, 2.57, 1, 1, 40, 63.25, -13.77, 1, 1, 40, 35.11, -24.6, 1, 2, 39, -27.45, 1.98, 3.0E-5, 40, 10.74, -18.07, 0.99997, 2, 39, 4.73, 18.99, 0.91829, 40, -23.41, -5.49, 0.08172, 1, 39, 37.75, 32.96, 1, 1, 39, 55.7, 16.34, 1 ],
					"hull": 12,
					"edges": [ 0, 2, 2, 4, 4, 6, 6, 8, 8, 10, 10, 12, 12, 14, 14, 16, 16, 18, 18, 20, 20, 22, 0, 22 ],
					"width": 144,
					"height": 59
				}
			},
			"Hat1": {
				"Hat1": {
					"type": "mesh",
					"uvs": [ 0.05612, 0, 0.12486, 0, 0.18817, 0.06697, 0.23697, 0.14866, 0.29213, 0.2223, 0.36098, 0.29049, 0.43925, 0.34329, 0.52328, 0.36623, 0.59953, 0.35388, 0.67611, 0.32328, 0.76734, 0.28749, 0.85639, 0.25587, 0.93759, 0.24771, 1, 0.29871, 0.99625, 0.4306, 0.95266, 0.5436, 0.8896, 0.65065, 0.81809, 0.73736, 0.75027, 0.8138, 0.68278, 0.87458, 0.61762, 0.92667, 0.53574, 0.9781, 0.44946, 1, 0.33403, 1, 0.25276, 0.94986, 0.18409, 0.8681, 0.11312, 0.76005, 0.06228, 0.61764, 0.02062, 0.45974, 0, 0.26097, 0, 0.09061 ],
					"triangles": [ 15, 11, 12, 15, 16, 11, 15, 12, 14, 14, 12, 13, 17, 9, 10, 17, 18, 9, 16, 10, 11, 16, 17, 10, 7, 21, 22, 7, 22, 6, 21, 7, 20, 7, 8, 20, 20, 8, 19, 8, 9, 19, 19, 9, 18, 6, 22, 23, 23, 5, 6, 23, 24, 5, 24, 25, 5, 25, 4, 5, 25, 26, 4, 4, 27, 3, 4, 26, 27, 28, 3, 27, 3, 28, 2, 2, 28, 1, 0, 1, 29, 1, 28, 29, 29, 30, 0 ],
					"vertices": [ 1, 35, 131.83, -6.45, 1, 1, 35, 113.51, -30.51, 1, 2, 35, 86.03, -44.6, 0.99582, 34, 150.52, -73.13, 0.00418, 3, 35, 60.09, -51.83, 0.93871, 34, 123.74, -70.31, 0.05937, 36, -84.46, 150.44, 0.00192, 3, 35, 33.72, -62.27, 0.71016, 34, 95.39, -70.31, 0.26833, 36, -64.28, 130.52, 0.02152, 3, 35, 4.57, -78.15, 0.31825, 34, 62.44, -74.35, 0.56822, 36, -38, 110.25, 0.11353, 4, 35, -24.65, -99.18, 0.07698, 34, 27.53, -83.15, 0.54427, 36, -6.97, 91.99, 0.37447, 37, -70.13, 114.65, 0.00429, 4, 35, -50.68, -125.83, 0.00825, 34, -6.49, -98.35, 0.23926, 36, 27.91, 78.91, 0.69238, 37, -39.95, 92.8, 0.06011, 4, 35, -69.05, -154.01, 7.0E-5, 34, -33.94, -117.79, 0.05797, 36, 61.11, 73.46, 0.68226, 37, -9.39, 78.75, 0.25969, 4, 34, -59.64, -140.42, 0.00597, 36, 95.3, 71.51, 0.35755, 37, 23.06, 67.82, 0.63521, 38, -49.4, 82.84, 0.00127, 3, 36, 135.99, 69.05, 0.05264, 37, 61.65, 54.68, 0.85743, 38, -15.33, 60.45, 0.08992, 3, 36, 175.55, 66.02, 1.5E-4, 37, 99, 41.27, 0.40357, 38, 17.46, 38.11, 0.59629, 2, 37, 131.08, 25.45, 0.00775, 38, 44.54, 14.75, 0.99225, 1, 38, 57.53, -11.49, 1, 1, 38, 38.31, -29.43, 1, 2, 37, 108.46, -29.32, 0.16803, 38, 8.92, -32.6, 0.83197, 2, 37, 73.88, -34.58, 0.90512, 38, -25.88, -29.02, 0.09488, 1, 37, 37.99, -34.5, 1, 2, 36, 104.21, -31.03, 0.27938, 37, 4.51, -33.42, 0.72062, 2, 36, 72.51, -35.85, 0.93754, 37, -27.33, -29.67, 0.06246, 1, 36, 42.22, -39.23, 1, 2, 34, -74.11, 3.06, 0.03808, 36, 4.79, -40.76, 0.96192, 2, 34, -43.86, 26.41, 0.48563, 36, -33.14, -36.13, 0.51437, 2, 34, -0.38, 52.66, 0.98287, 36, -82.52, -24.26, 0.01713, 2, 35, -70.97, 39.24, 0.00675, 34, 35.39, 62.6, 0.99325, 2, 35, -39.72, 53.42, 0.14537, 34, 69.67, 64.28, 0.85463, 2, 35, -3.69, 65.23, 0.57317, 34, 107.51, 62.02, 0.42683, 2, 35, 32.41, 65.86, 0.90557, 34, 141.31, 49.31, 0.09443, 2, 35, 68.51, 61.4, 0.9975, 34, 173.24, 31.89, 0.0025, 1, 35, 105.48, 44.66, 1, 1, 35, 132.45, 24.12, 1 ],
					"hull": 31,
					"edges": [ 0, 2, 2, 4, 4, 6, 6, 8, 8, 10, 10, 12, 12, 14, 14, 16, 16, 18, 18, 20, 20, 22, 22, 24, 24, 26, 26, 28, 28, 30, 30, 32, 32, 34, 34, 36, 36, 38, 38, 40, 40, 42, 42, 44, 44, 46, 46, 48, 48, 50, 50, 52, 52, 54, 54, 56, 56, 58, 58, 60, 0, 60 ],
					"width": 440,
					"height": 199
				}
			},
			"Hu": {
				"Hu": {
					"type": "mesh",
					"uvs": [ 0.07203, 1.0E-5, 0.03285, 0.16534, 1.0E-5, 0.3018, 0.00542, 0.55379, 0.05757, 0.79988, 0.14824, 0.9296, 0.25433, 0.96953, 0.3665, 0.87721, 0.43423, 0.69432, 0.46994, 0.68813, 0.53575, 0.87423, 0.62648, 0.99662, 0.74232, 1, 0.86845, 0.93612, 0.93915, 0.7669, 1, 0.54502, 1, 0.35079, 0.98571, 0.14106, 0.94849, 0, 0.85613, 0.00673, 0.81113, 0.24315, 0.73507, 0.35221, 0.64197, 0.35311, 0.54238, 0.29747, 0.4643, 0.31933, 0.40866, 0.3205, 0.33864, 0.32082, 0.26164, 0.34232, 0.2007, 0.31462, 0.1595, 0.16369, 0.14458, 0.00606 ],
					"triangles": [ 5, 28, 27, 29, 28, 3, 28, 5, 4, 30, 29, 1, 30, 1, 0, 3, 28, 4, 29, 2, 1, 29, 3, 2, 6, 5, 27, 6, 27, 7, 27, 26, 7, 8, 26, 25, 8, 7, 26, 8, 25, 24, 13, 12, 21, 22, 21, 12, 13, 21, 14, 14, 21, 20, 14, 20, 16, 15, 14, 16, 17, 19, 18, 16, 20, 17, 19, 17, 20, 12, 11, 22, 11, 10, 22, 22, 9, 23, 22, 10, 9, 8, 24, 9, 9, 24, 23 ],
					"vertices": [ 3, 26, 55.92, -90.61, 0.00852, 27, 72.02, -59.5, 0.02623, 28, 59.13, -36.88, 0.96525, 3, 26, 74.18, -79.02, 9.6E-4, 27, 79.85, -39.35, 0.02409, 28, 57.08, -15.35, 0.97495, 3, 26, 89.37, -69.51, 0.00222, 27, 86.46, -22.69, 0.07143, 28, 55.5, 2.5, 0.92634, 4, 23, -118.65, -59.81, 1.2E-4, 26, 101.11, -43.53, 0.01813, 27, 80.52, 5.2, 0.17307, 28, 37.67, 24.75, 0.80868, 4, 23, -94.23, -79.48, 0.00496, 26, 101.01, -12.17, 0.06717, 27, 61.86, 30.4, 0.30339, 28, 9.68, 38.89, 0.62448, 4, 23, -65.26, -82.82, 0.02862, 26, 85.36, 12.43, 0.16317, 27, 34.67, 40.94, 0.39996, 28, -19.35, 36.1, 0.40825, 5, 23, -36.43, -75.14, 0.09493, 24, -101.12, -39.36, 0.00215, 26, 61.24, 29.99, 0.28199, 27, 4.83, 40.79, 0.40477, 28, -45.93, 22.56, 0.21616, 6, 23, -12.03, -53.09, 0.21332, 24, -70.13, -28.36, 0.01745, 25, -112.36, 24.93, 1.0E-5, 26, 28.75, 35.05, 0.3682, 27, -24.34, 25.61, 0.31372, 28, -65.18, -4.1, 0.0873, 6, 23, -3.06, -26.62, 0.35526, 24, -51.69, -7.35, 0.06677, 25, -86.43, 35.38, 0.00236, 26, 2.53, 25.34, 0.3676, 27, -39.7, 2.25, 0.18341, 28, -68.42, -31.87, 0.02459, 6, 23, 5.76, -22, 0.45222, 24, -41.78, -6.47, 0.16434, 25, -77.18, 31.7, 0.01979, 26, -6.61, 29.28, 0.2829, 27, -49.4, 0.01, 0.07685, 28, -76.08, -38.23, 0.0039, 6, 23, 30.94, -33.94, 0.44846, 24, -23.1, -27.16, 0.28898, 25, -69.82, 4.81, 0.07734, 26, -13.2, 56.37, 0.16398, 27, -70.76, 17.92, 0.02109, 28, -103.21, -31.81, 1.4E-4, 5, 23, 59.6, -36.51, 0.34488, 24, 2.38, -40.52, 0.3801, 25, -53.1, -18.59, 0.20303, 26, -29.25, 80.24, 0.06924, 27, -97.83, 27.64, 0.00275, 5, 23, 89.26, -23.96, 0.20301, 24, 34.58, -40.31, 0.38214, 25, -24.25, -32.91, 0.39565, 26, -57.68, 95.37, 0.01919, 27, -129.7, 22.98, 1.0E-5, 4, 23, 118.49, -3.31, 0.08745, 24, 69.51, -32.45, 0.29257, 25, 10.47, -41.63, 0.61714, 26, -92.14, 105.07, 0.00283, 4, 23, 128.85, 22.09, 0.02556, 24, 88.81, -12.97, 0.16805, 25, 36.47, -32.93, 0.80639, 26, -118.38, 97.12, 0, 3, 23, 134.3, 51.84, 0.00405, 24, 105.26, 12.41, 0.06834, 25, 62.59, -17.68, 0.9276, 3, 23, 125.51, 71.95, 1.4E-4, 24, 104.85, 34.36, 0.01903, 25, 72.12, 2.09, 0.98083, 3, 23, 112.38, 92.07, 3.8E-4, 24, 100.45, 57.98, 0.01267, 25, 78.83, 25.17, 0.98695, 3, 23, 96.52, 102.53, 0.0074, 24, 89.81, 73.73, 0.0422, 25, 76.42, 44.02, 0.9504, 4, 23, 73.29, 91.55, 0.03921, 24, 64.15, 72.49, 0.10574, 25, 52.96, 54.48, 0.85505, 26, -137.35, 10.21, 0, 4, 23, 72.53, 62.06, 0.12148, 24, 52.13, 45.55, 0.18532, 25, 30.1, 35.84, 0.68986, 26, -113.96, 28.2, 0.00334, 5, 23, 58.09, 42.3, 0.25856, 24, 31.22, 32.84, 0.24076, 25, 5.7, 33.91, 0.47723, 26, -89.52, 29.43, 0.02341, 27, -116.27, -49.01, 3.0E-5, 6, 23, 34.42, 31.85, 0.40724, 24, 5.34, 32.26, 0.23613, 25, -17.66, 45.05, 0.27053, 26, -66.48, 17.63, 0.08465, 27, -90.72, -44.86, 0.00136, 28, -92.85, -96.87, 9.0E-5, 6, 23, 6.53, 26.52, 0.49054, 24, -22.45, 38.04, 0.17435, 25, -39.88, 62.73, 0.11899, 26, -44.78, -0.68, 0.20307, 27, -62.39, -46.74, 0.01081, 28, -66.69, -85.83, 0.00223, 6, 23, -12.37, 15.56, 0.45778, 24, -44.11, 35.17, 0.09472, 25, -60.51, 69.93, 0.0373, 26, -24.37, -8.46, 0.35524, 27, -41.33, -40.91, 0.03871, 28, -50.5, -71.17, 0.01624, 6, 23, -26.49, 9.25, 0.32967, 24, -59.57, 34.75, 0.03521, 25, -74.5, 76.52, 0.00709, 26, -10.57, -15.44, 0.47367, 27, -26.08, -38.36, 0.09082, 28, -38.01, -62.04, 0.06354, 6, 23, -44.31, 1.42, 0.17946, 24, -79.03, 34.36, 0.00785, 25, -92.05, 84.93, 4.0E-4, 26, 6.74, -24.35, 0.49118, 27, -6.86, -35.28, 0.15065, 28, -22.22, -50.66, 0.17045, 5, 23, -62.95, -9.38, 0.07036, 24, -100.39, 31.54, 4.5E-4, 26, 26.87, -32.03, 0.39765, 27, 13.91, -29.54, 0.1874, 28, -6.25, -36.2, 0.34414, 4, 23, -79.73, -13.3, 0.01798, 26, 40.48, -42.59, 0.24899, 27, 31.13, -29.98, 0.17619, 28, 9.34, -28.86, 0.55684, 4, 23, -97.06, -2.26, 0.00224, 26, 42.82, -63.01, 0.11731, 27, 45.11, -45.03, 0.12554, 28, 28.59, -36.03, 0.75491, 3, 26, 38.32, -80.73, 0.03951, 27, 51.99, -61.98, 0.06559, 28, 42.34, -48.08, 0.8949 ],
					"hull": 31,
					"edges": [ 0, 2, 2, 4, 4, 6, 6, 8, 8, 10, 10, 12, 12, 14, 14, 16, 16, 18, 18, 20, 20, 22, 22, 24, 24, 26, 26, 28, 28, 30, 30, 32, 32, 34, 34, 36, 36, 38, 38, 40, 40, 42, 42, 44, 44, 46, 46, 48, 48, 50, 50, 52, 52, 54, 54, 56, 56, 58, 58, 60, 0, 60 ],
					"width": 278,
					"height": 113
				}
			},
			"Lf": {
				"F_L": {
					"type": "mesh",
					"uvs": [ 0, 0.03153, 1.0E-5, 0.26653, 1.0E-5, 0.49653, 0.03843, 0.76528, 0.16593, 0.96778, 0.47843, 0.985, 0.74468, 0.99999, 1, 1, 0.98875, 0.70152, 1, 0.43028, 0.99999, 0.22028, 1, 0, 0.45968, 1.6E-4, 0.52968, 0.44407, 0.54718, 0.73779, 0.49968, 0.24034 ],
					"triangles": [ 6, 8, 7, 5, 14, 6, 6, 14, 8, 5, 4, 14, 4, 3, 14, 14, 3, 13, 3, 2, 13, 14, 13, 8, 8, 13, 9, 13, 2, 1, 13, 1, 15, 9, 13, 10, 13, 15, 10, 1, 12, 15, 1, 0, 12, 10, 15, 11, 11, 15, 12 ],
					"vertices": [ 2, 20, -3.75, -37.38, 0.97907, 21, -33.45, -39.23, 0.02093, 2, 20, 14.92, -39.63, 0.8454, 21, -14.7, -40.48, 0.1546, 3, 20, 33.19, -41.83, 0.51273, 21, 3.66, -41.69, 0.4865, 22, -48.63, 1.62, 7.7E-4, 3, 20, 54.9, -41.35, 0.17045, 21, 25.32, -40.05, 0.76717, 22, -36.65, -16.5, 0.06238, 3, 20, 72.2, -33.16, 0.0409, 21, 42.16, -30.94, 0.72392, 22, -20.5, -26.77, 0.23518, 2, 21, 45.19, -6.08, 0.13358, 22, 2.69, -17.32, 0.86642, 1, 22, 22.45, -9.28, 1, 3, 20, 82.74, 32.78, 2.7E-4, 21, 49.14, 35.47, 3.5E-4, 22, 40.91, -0.54, 0.99938, 3, 20, 58.93, 34.74, 0.1124, 21, 25.26, 36.15, 0.17431, 22, 29.87, 20.66, 0.71329, 3, 20, 37.49, 38.23, 0.52273, 21, 3.66, 38.48, 0.24244, 22, 21.4, 40.65, 0.23483, 3, 20, 20.81, 40.24, 0.85054, 21, -13.1, 39.59, 0.08884, 22, 14.21, 55.83, 0.06062, 3, 20, 3.32, 42.35, 0.97447, 21, -30.68, 40.76, 0.01399, 22, 6.66, 71.76, 0.01155, 1, 20, -1.85, -0.57, 1, 2, 21, 2.27, 0.87, 0.99857, 22, -12.14, 23.55, 0.00143, 2, 21, 25.81, 0.71, 0.98388, 22, -0.81, 2.91, 0.01612, 3, 20, 17.61, 0.31, 0.99997, 21, -14.15, -0.45, 1.0E-5, 22, -21.28, 37.25, 3.0E-5 ],
					"hull": 13,
					"edges": [ 0, 2, 2, 4, 4, 6, 6, 8, 8, 10, 10, 12, 12, 14, 14, 16, 16, 18, 18, 20, 20, 22, 22, 24, 24, 0, 4, 26, 26, 18, 6, 28, 28, 16, 2, 30, 30, 20 ],
					"width": 80,
					"height": 80
				}
			},
			"Lh_1": {
				"Lh_1": {
					"type": "mesh",
					"uvs": [ 0.08295, 1.0E-5, 0.26253, 0, 0.44308, 0.07048, 0.64692, 0.16487, 0.85375, 0.28552, 1, 0.40947, 1, 0.72486, 0.90045, 0.95496, 0.72633, 1, 0.49023, 1, 0.3941, 0.87589, 0.236, 0.74996, 0.0828, 0.65328, 0, 0.49079, 1.0E-5, 0.2312, 0.68413, 0.60783 ],
					"triangles": [ 7, 8, 15, 8, 9, 15, 9, 10, 15, 7, 15, 6, 6, 15, 5, 15, 4, 5, 3, 15, 2, 2, 15, 11, 11, 15, 10, 11, 12, 1, 11, 1, 2, 0, 1, 14, 12, 13, 1, 14, 1, 13, 15, 3, 4 ],
					"vertices": [ 1, 17, -1.49, 18.56, 1, 2, 17, 12.42, 23.38, 0.99697, 18, -47.18, -17.9, 0.00303, 2, 17, 27.82, 24.17, 0.93944, 18, -37.54, -5.86, 0.06056, 2, 17, 45.49, 24.21, 0.78892, 18, -25.83, 7.38, 0.21108, 2, 17, 63.93, 22.81, 0.53357, 18, -12.54, 20.23, 0.46643, 2, 17, 77.74, 19.6, 0.27611, 18, -0.97, 28.42, 0.72389, 2, 17, 84.04, 1.42, 0.09617, 18, 16.81, 21.06, 0.90383, 2, 17, 80.93, -14.51, 0.06763, 18, 26.66, 8.15, 0.93237, 2, 17, 68.34, -21.79, 0.17106, 18, 23.73, -6.09, 0.82894, 2, 17, 50.05, -28.13, 0.39321, 18, 16.33, -23.98, 0.60679, 2, 17, 40.12, -23.56, 0.63904, 18, 6.32, -28.37, 0.36096, 2, 17, 25.35, -20.55, 0.84526, 18, -5.74, -37.41, 0.15474, 2, 17, 11.55, -19.1, 0.95345, 18, -15.99, -46.76, 0.04655, 2, 17, 1.89, -11.96, 0.99453, 18, -27.75, -49.24, 0.00547, 2, 17, -3.3, 3, 0.99987, 18, -42.38, -43.18, 1.3E-4, 2, 17, 57.23, -0.32, 0.37292, 18, 0.31, -0.14, 0.62708 ],
					"hull": 15,
					"edges": [ 0, 2, 2, 4, 4, 6, 6, 8, 8, 10, 10, 12, 12, 14, 14, 16, 16, 18, 18, 20, 20, 22, 22, 24, 24, 26, 26, 28, 0, 28 ],
					"width": 82,
					"height": 61
				}
			},
			"Lh_2": {
				"Lh_2": {
					"type": "mesh",
					"uvs": [ 1.0E-5, 0.20989, 1.0E-5, 0.40328, 0.04794, 0.611, 0.10709, 0.82141, 0.17404, 1, 0.39946, 1, 0.67175, 0.96824, 0.8994, 0.89393, 1, 0.83573, 0.99999, 0.69785, 0.90052, 0.49371, 0.80678, 0.29495, 0.70411, 0.11409, 0.58025, 0, 0.32581, 1.0E-5, 0.09928, 0.05947, 0.29791, 0.24749 ],
					"triangles": [ 7, 9, 8, 9, 7, 6, 16, 15, 14, 0, 15, 16, 1, 0, 16, 2, 1, 16, 10, 3, 2, 16, 14, 13, 12, 16, 13, 16, 12, 11, 11, 10, 16, 9, 6, 10, 2, 16, 10, 6, 3, 10, 5, 4, 3, 6, 5, 3 ],
					"vertices": [ 3, 17, 42.52, -10.34, 0.53377, 18, -1.97, -17.79, 0.4608, 19, -67.16, -1.66, 0.00543, 3, 17, 47.97, -26.06, 0.37847, 18, 13.4, -24.15, 0.595, 19, -53.78, -11.54, 0.02652, 3, 17, 56.95, -41.85, 0.19485, 18, 31.17, -27.93, 0.72265, 19, -37.44, -19.48, 0.08249, 3, 17, 66.73, -57.61, 0.0686, 18, 49.45, -31.08, 0.73501, 19, -20.46, -26.94, 0.19639, 3, 17, 76.13, -70.61, 0.01499, 18, 65.41, -32.69, 0.62017, 19, -5.36, -32.35, 0.36484, 3, 17, 90.83, -65.51, 0.00173, 18, 71.35, -18.31, 0.44303, 19, 3.88, -19.83, 0.55525, 3, 17, 107.68, -56.77, 5.0E-5, 18, 76.02, 0.09, 0.31078, 19, 12.84, -3.1, 0.68917, 2, 18, 76.12, 17.05, 0.28409, 19, 17.03, 13.34, 0.71591, 2, 18, 74.15, 25.37, 0.38269, 19, 17.12, 21.89, 0.61731, 2, 18, 63.19, 29.91, 0.5562, 19, 7.58, 28.94, 0.4438, 3, 17, 109.22, -13.04, 8.3E-4, 18, 44.35, 30.28, 0.74143, 19, -10.62, 33.84, 0.25773, 3, 17, 97.51, 0.99, 0.01713, 18, 26.08, 30.85, 0.86721, 19, -28.21, 38.79, 0.11567, 3, 17, 85.72, 13.36, 0.08592, 18, 9, 30.25, 0.87748, 19, -44.93, 42.32, 0.0366, 3, 17, 74.43, 19.83, 0.23359, 18, -3.33, 26.11, 0.76002, 19, -57.9, 41.27, 0.00638, 3, 17, 57.85, 14.08, 0.42625, 18, -10.05, 9.88, 0.57334, 19, -68.33, 27.15, 4.1E-4, 3, 17, 44.75, 4.12, 0.55435, 18, -11.3, -6.51, 0.44539, 19, -73.5, 11.53, 2.6E-4, 2, 17, 63, -6.66, 4.7E-4, 18, 8.88, -0.04, 0.99953 ],
					"hull": 16,
					"edges": [ 0, 2, 2, 4, 4, 6, 6, 8, 8, 10, 10, 12, 12, 14, 14, 16, 16, 18, 18, 20, 20, 22, 22, 24, 24, 26, 26, 28, 28, 30, 0, 30 ],
					"width": 69,
					"height": 86
				}
			},
			"Lh_qt1": {
				"H_L_sz": {
					"type": "mesh",
					"uvs": [ 0.11828, 0.18131, 0.21975, 0.09532, 0.32398, 0.03755, 0.44998, 0.00622, 0.60489, 0.00889, 0.76961, 0.04222, 0.91551, 0.13979, 0.98278, 0.27409, 1, 0.42757, 1, 0.60024, 0.93718, 0.7053, 0.84076, 0.87796, 0.6454, 0.97028, 0.4688, 1, 0.33395, 0.85149, 0.33245, 0.62523, 0.21532, 0.51411, 0.12975, 0.35583, 0.51045, 0.25232, 0.64491, 0.46407 ],
					"triangles": [ 17, 0, 1, 2, 18, 1, 18, 2, 3, 18, 3, 4, 12, 14, 15, 11, 19, 10, 11, 12, 19, 13, 14, 12, 19, 5, 6, 19, 6, 7, 19, 7, 8, 19, 8, 9, 10, 19, 9, 19, 12, 15, 5, 18, 4, 19, 18, 5, 18, 16, 17, 15, 18, 19, 1, 18, 17, 15, 16, 18 ],
					"vertices": [ 1, 18, 57.75, -27.74, 1, 1, 18, 55.16, -15.79, 1, 1, 18, 54.78, -4.47, 1, 1, 18, 57.21, 8.03, 1, 1, 18, 63.27, 22.12, 1, 4, 19, 17.63, 32.87, 0.46966, 50, -16.44, 32.67, 0.11419, 51, -46.75, 5.86, 0.00814, 18, 72, 36.15, 0.408, 3, 19, 32.57, 39.8, 0.49633, 50, -1.51, 39.6, 0.43547, 51, -39, 20.38, 0.0682, 3, 19, 45.28, 38.7, 0.30684, 50, 11.2, 38.5, 0.52047, 51, -28.19, 27.15, 0.17269, 3, 19, 56.29, 32.69, 0.16032, 50, 22.21, 32.49, 0.49894, 51, -15.78, 28.99, 0.34074, 3, 19, 67.55, 24.38, 0.06722, 50, 33.47, 24.19, 0.37679, 51, -1.79, 29.13, 0.55599, 3, 19, 70.7, 14.32, 0.01988, 50, 36.63, 14.13, 0.22918, 51, 6.78, 23, 0.75094, 3, 19, 76.28, -1.66, 0.00347, 50, 42.21, -1.85, 0.13226, 51, 20.87, 13.6, 0.86427, 3, 19, 70.81, -21.66, 0.00763, 50, 36.75, -21.85, 0.1453, 51, 28.55, -5.66, 0.84706, 3, 19, 62.37, -37.16, 0.05964, 50, 28.31, -37.35, 0.23314, 51, 31.14, -23.11, 0.70723, 3, 19, 44.76, -40.76, 0.19983, 50, 10.7, -40.95, 0.30712, 51, 19.25, -36.59, 0.49305, 3, 19, 29.93, -29.99, 0.623, 50, -4.13, -30.19, 0.19755, 51, 0.92, -36.93, 0.17945, 1, 19, 15.8, -33.98, 1, 2, 19, 0.45, -33.18, 0.56, 18, 71.24, -32.1, 0.44, 1, 19, 16.09, 2.12, 1, 1, 50, 3.72, 2.45, 1 ],
					"hull": 18,
					"edges": [ 0, 2, 2, 4, 4, 6, 6, 8, 8, 10, 10, 12, 12, 14, 14, 16, 16, 18, 18, 20, 20, 22, 22, 24, 24, 26, 26, 28, 0, 34, 32, 34, 28, 30, 30, 32 ],
					"width": 99,
					"height": 81
				}
			},
			"Lh_qt2": {
				"H_L_sz1": {
					"type": "mesh",
					"uvs": [ 0.11828, 0.18131, 0.21975, 0.09532, 0.36075, 0.09051, 0.47427, 0.17955, 0.49787, 0.42456, 0.38487, 0.57184, 0.35969, 0.69534, 0.29661, 0.82502, 0.15066, 0.84789, 0.03036, 0.77792, 1.0E-5, 0.62839, 0.00722, 0.45609, 0.08543, 0.35393, 0.18479, 0.59877 ],
					"triangles": [ 6, 13, 5, 4, 2, 3, 4, 5, 2, 2, 5, 12, 12, 1, 2, 1, 12, 0, 7, 8, 13, 8, 9, 13, 7, 13, 6, 9, 10, 13, 10, 11, 13, 11, 12, 13, 5, 13, 12 ],
					"vertices": [ 1, 19, -11.59, -25.7, 1, 1, 19, -11.23, -13.48, 1, 1, 19, -3.26, -2.02, 1, 1, 19, 9.22, 2.74, 1, 1, 19, 26.58, -7.17, 1, 1, 19, 29.53, -23.25, 1, 3, 52, 17.42, 25.84, 0.62799, 53, 9.91, 23.91, 0.34752, 19, 36.1, -31.2, 0.02449, 3, 52, 29.5, 27.67, 0.35642, 53, 21.71, 20.75, 0.64258, 19, 40.84, -42.46, 0.001, 2, 52, 40.1, 17.67, 0.09327, 53, 27.41, 7.34, 0.90673, 2, 52, 43.27, 4.87, 7.2E-4, 53, 25.19, -5.66, 0.99928, 1, 53, 14.34, -11.83, 1, 2, 52, 24.57, -13.43, 0.09618, 53, 0.72, -14.93, 0.90382, 3, 52, 13.26, -12.7, 0.70033, 53, -9.35, -9.72, 0.29956, 19, -2.28, -36.62, 1.1E-4, 3, 52, 22.35, 7.49, 0.34031, 53, 7.07, 5.12, 0.65806, 19, 19.52, -40.48, 0.00163 ],
					"hull": 13,
					"edges": [ 0, 2, 2, 4, 4, 6, 6, 8, 8, 10, 14, 16, 16, 18, 18, 20, 20, 22, 22, 24, 0, 24, 10, 12, 12, 14 ],
					"width": 99,
					"height": 81
				}
			},
			"Rf": {
				"F_L": {
					"type": "mesh",
					"uvs": [ 0, 0.03153, 1.0E-5, 0.26653, 1.0E-5, 0.49653, 0.03843, 0.76528, 0.16593, 0.96778, 0.47843, 0.985, 0.74468, 0.99999, 1, 1, 0.98875, 0.70152, 1, 0.43028, 0.99999, 0.22028, 1, 0, 0.45968, 1.6E-4, 0.52968, 0.44407, 0.54718, 0.73779, 0.49968, 0.24034 ],
					"triangles": [ 6, 8, 7, 5, 14, 6, 6, 14, 8, 5, 4, 14, 4, 3, 14, 14, 3, 13, 3, 2, 13, 14, 13, 8, 8, 13, 9, 13, 2, 1, 13, 1, 15, 9, 13, 10, 13, 15, 10, 1, 12, 15, 1, 0, 12, 10, 15, 11, 11, 15, 12 ],
					"vertices": [ 2, 45, -3.75, -37.38, 0.97907, 46, -33.45, -39.23, 0.02093, 2, 45, 14.92, -39.63, 0.8454, 46, -14.7, -40.48, 0.1546, 3, 45, 33.19, -41.83, 0.51273, 46, 3.66, -41.69, 0.4865, 47, -48.63, 1.62, 7.7E-4, 3, 45, 54.9, -41.35, 0.17045, 46, 25.32, -40.05, 0.76717, 47, -36.65, -16.5, 0.06238, 3, 45, 72.2, -33.16, 0.0409, 46, 42.16, -30.94, 0.72392, 47, -20.5, -26.77, 0.23518, 2, 46, 45.19, -6.08, 0.13358, 47, 2.69, -17.32, 0.86642, 1, 47, 22.45, -9.28, 1, 3, 45, 82.74, 32.78, 2.7E-4, 46, 49.14, 35.47, 3.5E-4, 47, 40.91, -0.54, 0.99938, 3, 45, 58.93, 34.74, 0.1124, 46, 25.26, 36.15, 0.17431, 47, 29.87, 20.66, 0.71329, 3, 45, 37.49, 38.23, 0.52273, 46, 3.66, 38.48, 0.24244, 47, 21.4, 40.65, 0.23483, 3, 45, 20.81, 40.24, 0.85054, 46, -13.1, 39.59, 0.08884, 47, 14.21, 55.83, 0.06062, 3, 45, 3.32, 42.35, 0.97447, 46, -30.68, 40.76, 0.01399, 47, 6.66, 71.76, 0.01155, 1, 45, -1.85, -0.57, 1, 2, 46, 2.27, 0.87, 0.99857, 47, -12.14, 23.55, 0.00143, 2, 46, 25.81, 0.71, 0.98388, 47, -0.81, 2.91, 0.01612, 3, 45, 17.61, 0.31, 0.99997, 46, -14.15, -0.45, 1.0E-5, 47, -21.28, 37.25, 3.0E-5 ],
					"hull": 13,
					"edges": [ 0, 2, 2, 4, 4, 6, 6, 8, 8, 10, 10, 12, 12, 14, 14, 16, 16, 18, 18, 20, 20, 22, 22, 24, 24, 0, 4, 26, 26, 18, 6, 28, 28, 16, 2, 30, 30, 20 ],
					"width": 80,
					"height": 80
				}
			},
			"Rh_1": {
				"Lh_1": {
					"type": "mesh",
					"uvs": [ 0.08295, 1.0E-5, 0.26253, 0, 0.44308, 0.07048, 0.64692, 0.16487, 0.85375, 0.28552, 1, 0.40947, 1, 0.72486, 0.90045, 0.95496, 0.72633, 1, 0.49023, 1, 0.3941, 0.87589, 0.236, 0.74996, 0.0828, 0.65328, 0, 0.49079, 1.0E-5, 0.2312, 0.68413, 0.60783 ],
					"triangles": [ 7, 8, 15, 8, 9, 15, 9, 10, 15, 7, 15, 6, 6, 15, 5, 15, 4, 5, 3, 15, 2, 2, 15, 11, 11, 15, 10, 11, 12, 1, 11, 1, 2, 0, 1, 14, 12, 13, 1, 14, 1, 13, 15, 3, 4 ],
					"vertices": [ 1, 6, -1.49, 18.56, 1, 2, 6, 12.42, 23.38, 0.99697, 7, -47.18, -17.9, 0.00303, 2, 6, 27.82, 24.17, 0.93944, 7, -37.54, -5.86, 0.06056, 2, 6, 45.49, 24.21, 0.78892, 7, -25.83, 7.38, 0.21108, 2, 6, 63.93, 22.81, 0.53357, 7, -12.54, 20.23, 0.46643, 2, 6, 77.74, 19.6, 0.27611, 7, -0.97, 28.42, 0.72389, 2, 6, 84.04, 1.42, 0.09617, 7, 16.81, 21.06, 0.90383, 2, 6, 80.93, -14.51, 0.06763, 7, 26.66, 8.15, 0.93237, 2, 6, 68.34, -21.79, 0.17106, 7, 23.73, -6.09, 0.82894, 2, 6, 50.05, -28.13, 0.39321, 7, 16.33, -23.98, 0.60679, 2, 6, 40.12, -23.56, 0.63904, 7, 6.32, -28.37, 0.36096, 2, 6, 25.35, -20.55, 0.84526, 7, -5.74, -37.41, 0.15474, 2, 6, 11.55, -19.1, 0.95345, 7, -15.99, -46.76, 0.04655, 2, 6, 1.89, -11.96, 0.99453, 7, -27.75, -49.24, 0.00547, 2, 6, -3.3, 3, 0.99987, 7, -42.38, -43.18, 1.3E-4, 2, 6, 57.23, -0.32, 0.37292, 7, 0.31, -0.14, 0.62708 ],
					"hull": 15,
					"edges": [ 0, 2, 2, 4, 4, 6, 6, 8, 8, 10, 10, 12, 12, 14, 14, 16, 16, 18, 18, 20, 20, 22, 22, 24, 24, 26, 26, 28, 0, 28 ],
					"width": 82,
					"height": 61
				}
			},
			"Rh_2": {
				"Lh_2": {
					"type": "mesh",
					"uvs": [ 1.0E-5, 0.20989, 1.0E-5, 0.40328, 0.04794, 0.611, 0.10709, 0.82141, 0.17404, 1, 0.39946, 1, 0.67175, 0.96824, 0.8994, 0.89393, 1, 0.83573, 0.99999, 0.69785, 0.90052, 0.49371, 0.80678, 0.29495, 0.70411, 0.11409, 0.58025, 0, 0.32581, 1.0E-5, 0.09928, 0.05947, 0.29791, 0.24749 ],
					"triangles": [ 7, 9, 8, 9, 7, 6, 16, 15, 14, 0, 15, 16, 1, 0, 16, 2, 1, 16, 10, 3, 2, 16, 14, 13, 12, 16, 13, 16, 12, 11, 11, 10, 16, 9, 6, 10, 2, 16, 10, 6, 3, 10, 5, 4, 3, 6, 5, 3 ],
					"vertices": [ 3, 6, 42.52, -10.34, 0.53377, 7, -1.97, -17.79, 0.4608, 8, -67.16, -1.66, 0.00543, 3, 6, 47.97, -26.06, 0.37847, 7, 13.4, -24.15, 0.595, 8, -53.78, -11.54, 0.02652, 3, 6, 56.95, -41.85, 0.19485, 7, 31.17, -27.93, 0.72265, 8, -37.44, -19.48, 0.08249, 3, 6, 66.73, -57.61, 0.0686, 7, 49.45, -31.08, 0.73501, 8, -20.46, -26.94, 0.19639, 3, 6, 76.13, -70.61, 0.01499, 7, 65.41, -32.69, 0.62017, 8, -5.36, -32.35, 0.36484, 3, 6, 90.83, -65.51, 0.00173, 7, 71.35, -18.31, 0.44303, 8, 3.88, -19.83, 0.55525, 3, 6, 107.68, -56.77, 5.0E-5, 7, 76.02, 0.09, 0.31078, 8, 12.84, -3.1, 0.68917, 2, 7, 76.12, 17.05, 0.28409, 8, 17.03, 13.34, 0.71591, 2, 7, 74.15, 25.37, 0.38269, 8, 17.12, 21.89, 0.61731, 2, 7, 63.19, 29.91, 0.5562, 8, 7.58, 28.94, 0.4438, 3, 6, 109.22, -13.04, 8.3E-4, 7, 44.35, 30.28, 0.74143, 8, -10.62, 33.84, 0.25773, 3, 6, 97.51, 0.99, 0.01713, 7, 26.08, 30.85, 0.86721, 8, -28.21, 38.79, 0.11567, 3, 6, 85.72, 13.36, 0.08592, 7, 9, 30.25, 0.87748, 8, -44.93, 42.32, 0.0366, 3, 6, 74.43, 19.83, 0.23359, 7, -3.33, 26.11, 0.76002, 8, -57.9, 41.27, 0.00638, 3, 6, 57.85, 14.08, 0.42625, 7, -10.05, 9.88, 0.57334, 8, -68.33, 27.15, 4.1E-4, 3, 6, 44.75, 4.12, 0.55435, 7, -11.3, -6.51, 0.44539, 8, -73.5, 11.53, 2.6E-4, 2, 6, 63, -6.66, 4.7E-4, 7, 8.88, -0.04, 0.99953 ],
					"hull": 16,
					"edges": [ 0, 2, 2, 4, 4, 6, 6, 8, 8, 10, 10, 12, 12, 14, 14, 16, 16, 18, 18, 20, 20, 22, 22, 24, 24, 26, 26, 28, 28, 30, 0, 30 ],
					"width": 69,
					"height": 86
				}
			},
			"Rh_qt1": {
				"H_L_sz": {
					"type": "mesh",
					"uvs": [ 0.11828, 0.18131, 0.21975, 0.09532, 0.32398, 0.03755, 0.44998, 0.00622, 0.60489, 0.00889, 0.76961, 0.04222, 0.91551, 0.13979, 0.98278, 0.27409, 1, 0.42757, 1, 0.60024, 0.93718, 0.7053, 0.84076, 0.87796, 0.6454, 0.97028, 0.4688, 1, 0.33395, 0.85149, 0.33245, 0.62523, 0.21532, 0.51411, 0.12975, 0.35583, 0.51045, 0.25232, 0.64491, 0.46407 ],
					"triangles": [ 17, 0, 1, 2, 18, 1, 18, 2, 3, 18, 3, 4, 12, 14, 15, 11, 19, 10, 11, 12, 19, 13, 14, 12, 19, 5, 6, 19, 6, 7, 19, 7, 8, 19, 8, 9, 10, 19, 9, 19, 12, 15, 5, 18, 4, 19, 18, 5, 18, 16, 17, 15, 18, 19, 1, 18, 17, 15, 16, 18 ],
					"vertices": [ 1, 7, 57.75, -27.74, 1, 1, 7, 55.16, -15.79, 1, 1, 7, 54.78, -4.47, 1, 1, 7, 57.21, 8.03, 1, 1, 7, 63.27, 22.12, 1, 4, 8, 17.63, 32.87, 0.46966, 54, -16.44, 32.67, 0.11419, 55, -46.75, 5.86, 0.00814, 7, 72, 36.15, 0.408, 3, 8, 32.57, 39.8, 0.49633, 54, -1.51, 39.6, 0.43547, 55, -39, 20.38, 0.0682, 3, 8, 45.28, 38.7, 0.30684, 54, 11.2, 38.5, 0.52047, 55, -28.19, 27.15, 0.17269, 3, 8, 56.29, 32.69, 0.16032, 54, 22.21, 32.49, 0.49894, 55, -15.78, 28.99, 0.34074, 3, 8, 67.55, 24.38, 0.06722, 54, 33.47, 24.19, 0.37679, 55, -1.79, 29.13, 0.55599, 3, 8, 70.7, 14.32, 0.01988, 54, 36.63, 14.13, 0.22918, 55, 6.78, 23, 0.75094, 3, 8, 76.28, -1.66, 0.00347, 54, 42.21, -1.85, 0.13226, 55, 20.87, 13.6, 0.86427, 3, 8, 70.81, -21.66, 0.00763, 54, 36.75, -21.85, 0.1453, 55, 28.55, -5.66, 0.84706, 3, 8, 62.37, -37.16, 0.05964, 54, 28.31, -37.35, 0.23314, 55, 31.14, -23.11, 0.70723, 3, 8, 44.76, -40.76, 0.19983, 54, 10.7, -40.95, 0.30712, 55, 19.25, -36.59, 0.49305, 3, 8, 29.93, -29.99, 0.623, 54, -4.13, -30.19, 0.19755, 55, 0.92, -36.93, 0.17945, 1, 8, 15.8, -33.98, 1, 2, 8, 0.45, -33.18, 0.56, 7, 71.24, -32.1, 0.44, 1, 8, 16.09, 2.12, 1, 1, 54, 3.72, 2.45, 1 ],
					"hull": 18,
					"edges": [ 0, 2, 2, 4, 4, 6, 6, 8, 8, 10, 10, 12, 12, 14, 14, 16, 16, 18, 18, 20, 20, 22, 22, 24, 24, 26, 26, 28, 0, 34, 32, 34, 28, 30, 30, 32 ],
					"width": 99,
					"height": 81
				}
			},
			"Rh_qt2": {
				"H_L_sz1": {
					"type": "mesh",
					"uvs": [ 0.11828, 0.18131, 0.21975, 0.09532, 0.36075, 0.09051, 0.47427, 0.17955, 0.49787, 0.42456, 0.38487, 0.57184, 0.35969, 0.69534, 0.29661, 0.82502, 0.15066, 0.84789, 0.03036, 0.77792, 1.0E-5, 0.62839, 0.00722, 0.45609, 0.08543, 0.35393, 0.18479, 0.59877 ],
					"triangles": [ 6, 13, 5, 4, 2, 3, 4, 5, 2, 2, 5, 12, 12, 1, 2, 1, 12, 0, 7, 8, 13, 8, 9, 13, 7, 13, 6, 9, 10, 13, 10, 11, 13, 11, 12, 13, 5, 13, 12 ],
					"vertices": [ 1, 8, -11.59, -25.7, 1, 1, 8, -11.23, -13.48, 1, 1, 8, -3.26, -2.02, 1, 1, 8, 9.22, 2.74, 1, 1, 8, 26.58, -7.17, 1, 1, 8, 29.53, -23.25, 1, 3, 56, 17.42, 25.84, 0.62799, 57, 9.91, 23.91, 0.34752, 8, 36.1, -31.2, 0.02449, 3, 56, 29.5, 27.67, 0.35642, 57, 21.71, 20.75, 0.64258, 8, 40.84, -42.46, 0.001, 2, 56, 40.1, 17.67, 0.09327, 57, 27.41, 7.34, 0.90673, 2, 56, 43.27, 4.87, 7.2E-4, 57, 25.19, -5.66, 0.99928, 1, 57, 14.34, -11.83, 1, 2, 56, 24.57, -13.43, 0.09618, 57, 0.72, -14.93, 0.90382, 3, 56, 13.26, -12.7, 0.70033, 57, -9.35, -9.72, 0.29956, 8, -2.28, -36.62, 1.1E-4, 3, 56, 22.35, 7.49, 0.34031, 57, 7.07, 5.12, 0.65806, 8, 19.52, -40.48, 0.00163 ],
					"hull": 13,
					"edges": [ 0, 2, 2, 4, 4, 6, 6, 8, 8, 10, 14, 16, 16, 18, 18, 20, 20, 22, 22, 24, 0, 24, 10, 12, 12, 14 ],
					"width": 99,
					"height": 81
				}
			},
			"Wu_L": {
				"Wu_L": { "x": 49.82, "y": -10.79, "rotation": -88.97, "width": 64, "height": 80 }
			},
			"Wu_R": {
				"Wu_R": { "x": 44.37, "y": 15.54, "rotation": -88.97, "width": 65, "height": 79 }
			},
			"glass": {
				"glass": { "x": 12.11, "y": -0.09, "rotation": -94.37, "width": 132, "height": 111 }
			},
			"hat2": {
				"hat2": { "x": 18.69, "y": -16.16, "rotation": -87.41, "width": 308, "height": 242 }
			},
			"hat3": {
				"hat3": {
					"type": "mesh",
					"uvs": [ 0, 0.90516, 0, 1, 0.12747, 0.98228, 0.25077, 0.93764, 0.36813, 0.88311, 0.48494, 0.8231, 0.59003, 0.76379, 0.6889, 0.68667, 0.79173, 0.5983, 0.87401, 0.49467, 0.95045, 0.36812, 0.99999, 0.23877, 1, 0.07382, 0.93294, 1.0E-5, 0.80034, 1.0E-5, 0.70191, 0.05593, 0.60365, 0.13903, 0.5313, 0.22736, 0.46096, 0.33049, 0.38997, 0.45786, 0.30887, 0.60317, 0.21763, 0.72627, 0.1103, 0.83839 ],
					"triangles": [ 11, 13, 12, 11, 14, 13, 14, 10, 15, 11, 10, 14, 9, 15, 10, 16, 15, 9, 8, 16, 9, 17, 16, 8, 8, 7, 17, 7, 18, 17, 19, 18, 7, 6, 19, 7, 5, 20, 19, 6, 5, 19, 4, 20, 5, 21, 20, 4, 3, 21, 4, 22, 21, 3, 2, 22, 3, 0, 22, 2, 1, 0, 2 ],
					"vertices": [ 1, 36, 6.33, -19.54, 1, 1, 36, 2.12, -37.06, 1, 1, 36, 34.01, -41.26, 1, 2, 36, 66.09, -40.24, 0.96679, 37, -34.69, -32.21, 0.03321, 2, 36, 97.15, -37.05, 0.50075, 37, -3.9, -37.36, 0.49925, 2, 36, 128.32, -32.82, 0.03829, 37, 27.28, -41.52, 0.96171, 2, 37, 55.83, -44.39, 0.97739, 38, -45.81, -34, 0.02261, 2, 37, 84.63, -43.54, 0.69703, 38, -17.71, -40.39, 0.30297, 2, 37, 115.34, -41.3, 0.15737, 38, 12.58, -45.92, 0.84263, 2, 37, 142.93, -34.02, 0.00428, 38, 41.12, -45.79, 0.99572, 1, 38, 71.58, -41.49, 1, 1, 38, 97.5, -32.17, 1, 1, 38, 119.02, -9.4, 1, 1, 38, 116.42, 12.36, 1, 1, 38, 92.23, 35.22, 1, 2, 37, 145.35, 59.83, 0.00585, 38, 66.98, 44.47, 0.99415, 2, 37, 116.13, 57.91, 0.10394, 38, 38.21, 49.93, 0.89606, 2, 37, 92.12, 51.98, 0.38206, 38, 13.48, 50.21, 0.61794, 2, 37, 67.2, 43.35, 0.79978, 38, -12.81, 48.09, 0.20022, 2, 37, 39.91, 30.76, 0.99342, 38, -42.38, 42.74, 0.00658, 2, 36, 95.11, 18.14, 0.12252, 37, 8.76, 16.41, 0.87748, 1, 36, 67.38, 0.75, 1, 1, 36, 36.21, -13.67, 1 ],
					"hull": 23,
					"edges": [ 0, 2, 2, 4, 4, 6, 6, 8, 8, 10, 10, 12, 16, 18, 18, 20, 20, 22, 22, 24, 26, 28, 28, 30, 30, 32, 32, 34, 34, 36, 36, 38, 38, 40, 40, 42, 42, 44, 0, 44, 24, 26, 12, 14, 14, 16 ],
					"width": 251,
					"height": 190
				}
			},
			"tou_1": {
				"tou_1": {
					"type": "mesh",
					"uvs": [ 1.0E-5, 0.42477, 1.0E-5, 0.72058, 0.09205, 0.93383, 0.27306, 0.99999, 0.51695, 0.99999, 0.71072, 0.99781, 0.87446, 0.89377, 0.99999, 0.71641, 0.99999, 0.4145, 0.90607, 0.1649, 0.72997, 0.00109, 0.52331, 0, 0.32329, 0, 0.15649, 0.08206, 0.06147, 0.21504, 0.24222, 0.55292, 0.51799, 0.55183, 0.7725, 0.52131 ],
					"triangles": [ 17, 10, 9, 17, 9, 8, 16, 12, 11, 16, 11, 10, 16, 10, 17, 15, 13, 12, 15, 12, 16, 14, 13, 15, 0, 14, 15, 7, 17, 8, 1, 0, 15, 6, 17, 7, 2, 1, 15, 5, 16, 17, 5, 17, 6, 3, 15, 16, 4, 3, 16, 2, 15, 3, 5, 4, 16 ],
					"vertices": [ 2, 11, 119.89, 143.5, 0.9, 41, -105.98, 63.01, 0.1, 2, 11, 64.15, 147.76, 0.9, 41, -105.98, 7.1, 0.1, 2, 11, 21.79, 122.38, 0.9, 41, -77.45, -33.2, 0.1, 2, 11, 5.05, 67.38, 0.9, 41, -21.34, -45.71, 0.1, 2, 11, -0.71, -8.01, 0.9, 41, 54.27, -45.71, 0.1, 2, 11, -4.87, -67.93, 0.9, 41, 114.34, -45.3, 0.1, 2, 11, 10.87, -120.04, 0.9, 41, 165.1, -25.63, 0.1, 2, 11, 41.33, -161.4, 0.9, 41, 204.01, 7.89, 0.1, 2, 11, 98.23, -165.74, 0.9, 41, 204.01, 64.95, 0.1, 2, 11, 147.48, -140.3, 0.9, 41, 174.89, 112.12, 0.1, 2, 11, 182.51, -88.23, 0.9, 41, 120.3, 143.08, 0.1, 2, 11, 187.59, -24.36, 0.9, 41, 56.24, 143.29, 0.1, 2, 11, 192.31, 37.46, 0.9, 41, -5.77, 143.29, 0.1, 2, 11, 180.78, 90.2, 0.9, 41, -57.47, 127.78, 0.1, 2, 11, 157.97, 121.48, 0.9, 41, -86.93, 102.65, 0.1, 2, 11, 90.03, 70.48, 0.7, 41, -30.9, 38.79, 0.3, 2, 11, 83.72, -14.78, 0.7, 41, 54.59, 38.99, 0.3, 2, 11, 83.47, -93.89, 0.7, 41, 133.49, 44.76, 0.3 ],
					"hull": 15,
					"edges": [ 0, 2, 2, 4, 4, 6, 6, 8, 8, 10, 10, 12, 12, 14, 14, 16, 16, 18, 18, 20, 20, 22, 22, 24, 24, 26, 26, 28, 0, 28 ],
					"width": 310,
					"height": 189
				}
			},
			"tou_2": {
				"tou_2": {
					"type": "mesh",
					"uvs": [ 0.22191, 0.00705, 0.12701, 0.07081, 0.06133, 0.17009, 0.03113, 0.29472, 0.05887, 0.44628, 0.1015, 0.58705, 0.14781, 0.67819, 0.1597, 0.7546, 0.16624, 0.82205, 0.16856, 0.89861, 0.27562, 0.9615, 0.38797, 0.98197, 0.5128, 0.98104, 0.63407, 0.95732, 0.74404, 0.92289, 0.83559, 0.88893, 0.88374, 0.84334, 0.89562, 0.77216, 0.9087, 0.69307, 0.91584, 0.62189, 0.94518, 0.55035, 0.97563, 0.45119, 1, 0.30923, 1, 0.18955, 0.94924, 0.06965, 0.82824, 0.0144, 0.68322, 0, 0.536, 0.00115, 0.37037, 0, 0.51265, 0.72447, 0.53453, 0.33843, 0.53709, 0.12439, 0.53551, 0.21676, 0.52573, 0.46163, 0.52671, 0.61599, 0.51437, 0.86308, 0.31865, 0.85163, 0.32432, 0.72309, 0.71593, 0.69413, 0.70609, 0.83106, 0.2731, 0.32821, 0.79494, 0.32483, 0.30701, 0.1199, 0.75066, 0.11603, 0.30515, 0.61556, 0.73462, 0.59643, 0.2842, 0.46982, 0.76605, 0.46071 ],
					"triangles": [ 21, 41, 22, 30, 32, 41, 41, 32, 43, 32, 31, 43, 30, 40, 32, 3, 2, 40, 40, 2, 42, 40, 42, 32, 42, 2, 1, 22, 41, 23, 23, 41, 43, 23, 43, 24, 32, 42, 31, 42, 28, 31, 28, 27, 31, 31, 26, 43, 31, 27, 26, 1, 0, 42, 42, 0, 28, 43, 25, 24, 43, 26, 25, 6, 44, 37, 37, 44, 34, 38, 34, 45, 6, 5, 44, 19, 45, 20, 44, 33, 34, 34, 33, 45, 5, 46, 44, 44, 46, 33, 45, 47, 20, 45, 33, 47, 5, 4, 46, 20, 47, 21, 4, 40, 46, 33, 46, 30, 33, 30, 47, 30, 46, 40, 47, 41, 21, 47, 30, 41, 4, 3, 40, 35, 12, 11, 11, 10, 36, 12, 35, 13, 35, 11, 36, 10, 9, 36, 13, 39, 14, 13, 35, 39, 14, 39, 15, 9, 8, 36, 15, 39, 16, 35, 36, 29, 36, 37, 29, 35, 29, 39, 36, 8, 37, 16, 39, 17, 39, 38, 17, 39, 29, 38, 8, 7, 37, 17, 38, 18, 7, 6, 37, 29, 34, 38, 29, 37, 34, 18, 38, 19, 19, 38, 45 ],
					"vertices": [ 3, 13, 421.88, 120.76, 0, 14, 284.39, 115.94, 0.06361, 15, 149.56, 117.11, 0.93639, 3, 13, 391.03, 153.56, 4.9E-4, 14, 254.11, 149.26, 0.12226, 15, 119.01, 150.19, 0.87725, 3, 13, 344.34, 175.11, 0.00575, 14, 207.79, 171.61, 0.26964, 15, 72.52, 172.18, 0.72461, 3, 13, 286.57, 183.38, 0.0246, 14, 150.17, 180.85, 0.43962, 15, 14.83, 180.97, 0.53578, 3, 13, 217.38, 170.24, 0.09116, 14, 80.77, 168.9, 0.62253, 15, -54.48, 168.48, 0.28631, 3, 13, 153.39, 151.98, 0.25873, 14, 16.48, 151.72, 0.61388, 15, -118.63, 150.8, 0.12739, 3, 13, 112.26, 133.43, 0.52181, 14, -24.96, 133.87, 0.42837, 15, -159.93, 132.63, 0.04982, 3, 13, 77.34, 127.56, 0.66716, 14, -59.98, 128.6, 0.31156, 15, -194.9, 127.09, 0.02128, 3, 13, 46.46, 123.81, 0.82288, 14, -90.92, 125.37, 0.1719, 15, -225.82, 123.61, 0.00523, 3, 13, 11.31, 121.38, 0.89132, 14, -126.1, 123.54, 0.10732, 15, -260.99, 121.51, 0.00136, 3, 13, -15.85, 81.57, 0.94322, 14, -153.93, 84.19, 0.05657, 15, -288.51, 81.95, 2.1E-4, 3, 13, -23.42, 40.73, 0.97523, 14, -162.2, 43.5, 0.02475, 15, -296.46, 41.19, 2.0E-5, 2, 13, -20.96, -4.14, 0.99102, 14, -160.5, -1.41, 0.00898, 2, 13, -8.08, -47.26, 0.99401, 14, -148.36, -44.74, 0.00599, 3, 13, 9.53, -86.09, 0.98595, 14, -131.41, -83.87, 0.014, 15, -264.68, -85.93, 5.0E-5, 3, 13, 26.63, -118.3, 0.96581, 14, -114.86, -116.37, 0.03367, 15, -247.88, -118.3, 5.2E-4, 3, 13, 48.36, -134.67, 0.92757, 14, -93.4, -133.1, 0.06968, 15, -226.29, -134.87, 0.00275, 3, 13, 81.27, -137.46, 0.87125, 14, -60.55, -136.46, 0.12002, 15, -193.42, -137.97, 0.00874, 3, 13, 117.82, -140.52, 0.7405, 14, -24.06, -140.13, 0.23034, 15, -156.89, -141.36, 0.02916, 3, 13, 150.65, -141.6, 0.60707, 14, 8.75, -141.77, 0.33245, 15, -124.08, -142.74, 0.06048, 3, 13, 184, -150.67, 0.35381, 14, 41.94, -151.4, 0.50542, 15, -90.81, -152.11, 0.14077, 3, 13, 230.06, -159.55, 0.16904, 14, 87.85, -161.07, 0.52435, 15, -44.83, -161.42, 0.3066, 3, 13, 295.7, -165.36, 0.07011, 14, 153.37, -167.99, 0.36242, 15, 20.75, -167.83, 0.56747, 3, 13, 350.69, -162.87, 0.02945, 14, 208.4, -166.43, 0.20666, 15, 75.76, -165.85, 0.76389, 3, 13, 404.96, -142.12, 0.00683, 14, 263.02, -146.61, 0.08359, 15, 130.22, -145.6, 0.90958, 3, 13, 428.38, -97.45, 0.00135, 14, 287.19, -102.34, 0.0372, 15, 154.05, -101.15, 0.96145, 3, 13, 432.63, -45, 1.5E-4, 14, 292.33, -49.97, 0.01591, 15, 158.79, -48.74, 0.98394, 3, 13, 429.71, 7.92, 0, 14, 290.3, 2.99, 0.01359, 15, 156.34, 4.21, 0.98641, 2, 14, 289.15, 62.61, 0.02905, 15, 154.72, 63.81, 0.97095, 3, 13, 96.94, 1.26, 0.73028, 14, -42.52, 1.98, 0.25329, 15, -176.47, 0.61, 0.01643, 3, 13, 274.69, 1.43, 0.01444, 14, 135.2, -0.87, 0.3959, 15, 1.28, -0.86, 0.58966, 3, 13, 373.09, 4.97, 1.5E-4, 14, 233.65, 1, 0.04392, 15, 99.71, 1.77, 0.95593, 2, 14, 191.16, 0.36, 2.0E-5, 15, 57.22, 0.81, 0.99998, 3, 13, 217.93, 2.03, 0.06566, 14, 78.46, 0.7, 0.7545, 15, -55.47, 0.26, 0.17984, 3, 13, 147.02, -1.54, 0.23942, 14, 7.5, -1.67, 0.70585, 15, -126.41, -2.65, 0.05473, 3, 13, 33.27, -2.25, 0.93297, 14, -106.24, -0.44, 0.0663, 15, -240.16, -2.31, 7.2E-4, 3, 13, 35.34, 68.38, 0.89482, 14, -102.97, 70.14, 0.10377, 15, -237.44, 68.29, 0.00141, 3, 13, 94.51, 69.02, 0.65719, 14, -43.81, 69.77, 0.31944, 15, -178.28, 68.38, 0.02337, 3, 13, 114.2, -71.22, 0.70817, 14, -26.5, -70.78, 0.26226, 15, -159.88, -72.02, 0.02957, 3, 13, 51.11, -70.53, 0.92175, 14, -89.57, -69.02, 0.07548, 15, -222.95, -70.75, 0.00277, 3, 13, 275.13, 95.66, 0.01017, 14, 137.24, 93.34, 0.41739, 15, 2.58, 93.37, 0.57244, 3, 13, 285.19, -91.94, 0.03336, 14, 144.11, -94.4, 0.37345, 15, 10.91, -94.32, 0.59319, 3, 13, 371.41, 87.8, 0, 14, 233.37, 83.85, 0.06866, 15, 98.78, 84.62, 0.93134, 3, 13, 380.42, -71.67, 0.00135, 14, 239.67, -75.75, 0.04778, 15, 106.32, -74.93, 0.95087, 3, 13, 143.61, 78.15, 0.22015, 14, 5.44, 78.07, 0.70642, 15, -129.09, 77.07, 0.07343, 3, 13, 159.4, -75.9, 0.2848, 14, 18.61, -76.23, 0.63437, 15, -114.72, -77.13, 0.08083, 3, 13, 210.24, 88.72, 0.05707, 14, 72.24, 87.5, 0.7355, 15, -62.37, 87.02, 0.20743, 3, 13, 222.28, -84.38, 0.10779, 14, 81.34, -85.77, 0.67511, 15, -51.93, -86.18, 0.2171 ],
					"hull": 29,
					"edges": [ 0, 2, 2, 4, 4, 6, 6, 8, 10, 12, 12, 14, 14, 16, 16, 18, 18, 20, 20, 22, 22, 24, 24, 26, 26, 28, 28, 30, 30, 32, 32, 34, 34, 36, 36, 38, 38, 40, 42, 44, 44, 46, 46, 48, 48, 50, 50, 52, 52, 54, 54, 56, 0, 56, 16, 72, 72, 70, 12, 74, 74, 58, 38, 76, 76, 58, 34, 78, 78, 70, 6, 80, 80, 60, 44, 82, 82, 60, 2, 84, 84, 62, 48, 86, 86, 62, 10, 88, 88, 68, 68, 90, 90, 40, 8, 92, 92, 66, 66, 94, 94, 42, 8, 10, 40, 42 ],
					"width": 360,
					"height": 460
				}
			},
			"tou_3": {
				"tou_di": {
					"type": "mesh",
					"uvs": [ 1.0E-5, 0.42477, 1.0E-5, 0.72058, 0.09205, 0.93383, 0.27306, 0.99999, 0.51695, 0.99999, 0.71072, 0.99781, 0.87446, 0.89377, 0.99999, 0.71641, 0.99999, 0.4145, 0.90607, 0.1649, 0.72997, 0.00109, 0.52331, 0, 0.32329, 0, 0.15649, 0.08206, 0.06147, 0.21504, 0.24222, 0.55292, 0.51799, 0.55183, 0.7725, 0.52131 ],
					"triangles": [ 5, 4, 16, 2, 15, 3, 4, 3, 16, 3, 15, 16, 5, 17, 6, 5, 16, 17, 2, 1, 15, 6, 17, 7, 1, 0, 15, 7, 17, 8, 0, 14, 15, 14, 13, 15, 15, 12, 16, 15, 13, 12, 16, 10, 17, 16, 11, 10, 16, 12, 11, 17, 9, 8, 17, 10, 9 ],
					"vertices": [ 2, 11, 119.89, 143.5, 0.9, 41, -105.98, 63.01, 0.1, 2, 11, 64.15, 147.76, 0.9, 41, -105.98, 7.1, 0.1, 2, 11, 21.79, 122.38, 0.9, 41, -77.45, -33.2, 0.1, 2, 11, 5.05, 67.38, 0.9, 41, -21.34, -45.71, 0.1, 2, 11, -0.71, -8.01, 0.9, 41, 54.27, -45.71, 0.1, 2, 11, -4.87, -67.93, 0.9, 41, 114.34, -45.3, 0.1, 2, 11, 10.87, -120.04, 0.9, 41, 165.1, -25.63, 0.1, 2, 11, 41.33, -161.4, 0.9, 41, 204.01, 7.89, 0.1, 2, 11, 98.23, -165.74, 0.9, 41, 204.01, 64.95, 0.1, 2, 11, 147.48, -140.3, 0.9, 41, 174.89, 112.12, 0.1, 2, 11, 182.51, -88.23, 0.9, 41, 120.3, 143.08, 0.1, 2, 11, 187.59, -24.36, 0.9, 41, 56.24, 143.29, 0.1, 2, 11, 192.31, 37.46, 0.9, 41, -5.77, 143.29, 0.1, 2, 11, 180.78, 90.2, 0.9, 41, -57.47, 127.78, 0.1, 2, 11, 157.97, 121.48, 0.9, 41, -86.93, 102.65, 0.1, 2, 11, 90.03, 70.48, 0.7, 41, -30.9, 38.79, 0.3, 2, 11, 83.72, -14.78, 0.7, 41, 54.59, 38.99, 0.3, 2, 11, 83.47, -93.89, 0.7, 41, 133.49, 44.76, 0.3 ],
					"hull": 15,
					"edges": [ 0, 2, 2, 4, 4, 6, 6, 8, 8, 10, 10, 12, 12, 14, 14, 16, 16, 18, 18, 20, 20, 22, 22, 24, 24, 26, 26, 28, 0, 28 ],
					"width": 310,
					"height": 189
				}
			},
			"yand": {
				"yand": { "x": -39, "y": -53.21, "rotation": -94.37, "width": 138, "height": 98 }
			},
			"yifuwai": {
				"yifuwai": {
					"type": "mesh",
					"uvs": [ 0.17802, 0.89926, 0.17472, 0.97241, 0.22375, 1, 0.2709, 1, 0.32417, 1, 0.4562, 1, 0.583, 1, 0.64835, 1, 0.7285, 0.9874, 0.80696, 0.96272, 0.79188, 0.84813, 0.78339, 0.72914, 0.76972, 0.59957, 0.74614, 0.47882, 0.71314, 0.36247, 0.65515, 0.3801, 0.59575, 0.40302, 0.53965, 0.42153, 0.45381, 0.41924, 0.37416, 0.41712, 0.32985, 0.39949, 0.28553, 0.38891, 0.25111, 0.38274, 0.2464, 0.48763, 0.2398, 0.58635, 0.22377, 0.66744, 0.19171, 0.68683, 0.18134, 0.7882, 0.45148, 0.68683, 0.34823, 0.68771, 0.55473, 0.68331 ],
					"triangles": [ 8, 11, 10, 8, 10, 9, 30, 12, 11, 11, 7, 30, 7, 6, 30, 5, 30, 6, 11, 8, 7, 30, 17, 16, 28, 18, 17, 28, 17, 30, 13, 15, 14, 13, 16, 15, 12, 30, 16, 16, 13, 12, 5, 28, 30, 25, 27, 26, 0, 27, 3, 2, 0, 3, 1, 0, 2, 25, 3, 27, 25, 29, 3, 4, 3, 29, 29, 28, 5, 4, 29, 5, 23, 22, 21, 28, 19, 18, 29, 20, 19, 29, 19, 28, 23, 21, 20, 23, 20, 29, 24, 23, 29, 25, 24, 29 ],
					"vertices": [ 1, 43, 63.82, -42.75, 1, 1, 43, 82.19, -39.99, 1, 1, 43, 83.62, -15.81, 1, 3, 43, 78.46, 5.89, 0.99539, 31, 87.61, -195.88, 2.9E-4, 32, 8.48, -197.66, 0.00431, 4, 42, 131.45, 24.77, 0.00126, 43, 72.63, 30.4, 0.94687, 31, 93.72, -171.43, 0.00784, 32, 16.96, -173.93, 0.04403, 4, 42, 121.69, 86.45, 0.05791, 43, 58.18, 91.16, 0.52844, 31, 108.86, -110.85, 0.06769, 32, 37.96, -115.12, 0.34596, 4, 42, 112.31, 145.69, 0.0227, 43, 44.31, 149.51, 0.14118, 31, 123.41, -52.66, 0.0316, 32, 58.13, -58.64, 0.80451, 4, 42, 107.48, 176.22, 0.00348, 43, 37.16, 179.58, 0.03473, 31, 130.91, -22.68, 7.3E-4, 32, 68.53, -29.53, 0.96106, 1, 32, 78.28, 7.25, 1, 1, 32, 84.88, 44.3, 1, 2, 31, 110.1, 52.5, 0.01538, 32, 55.18, 47.33, 0.98462, 2, 31, 79.92, 55.91, 0.19805, 32, 25.48, 53.67, 0.80195, 2, 31, 46.55, 57.59, 0.64147, 32, -7.57, 58.61, 0.35853, 2, 31, 14.21, 54.18, 0.93433, 32, -40.09, 58.38, 0.06567, 2, 31, -18.14, 46.17, 0.99944, 32, -73.06, 53.58, 5.6E-4, 1, 31, -20.46, 18.48, 1, 2, 42, -37.81, 128.03, 0.03981, 31, -21.65, -10.18, 0.96019, 4, 42, -29.03, 102.55, 0.21697, 43, -93.33, 95.7, 0.00175, 31, -23.55, -37.06, 0.77997, 32, -86.59, -28.72, 0.0013, 4, 42, -23.26, 62.36, 0.59712, 43, -84.5, 56.07, 0.00206, 31, -33.95, -76.31, 0.3969, 32, -100.79, -66.76, 0.00392, 3, 42, -17.9, 25.07, 0.89853, 31, -43.61, -112.73, 0.10119, 32, -113.97, -102.06, 2.8E-4, 2, 42, -19.03, 3.67, 0.98682, 31, -53.02, -131.98, 0.01318, 1, 42, -18.39, -17.46, 1, 1, 42, -17.39, -33.78, 1, 2, 42, 9.17, -31.83, 0.99806, 43, -44.98, -35.37, 0.00194, 2, 42, 34.33, -31.01, 0.86524, 43, -19.95, -32.63, 0.13476, 2, 42, 55.77, -35.29, 0.32105, 43, 1.76, -35.26, 0.67895, 2, 42, 62.99, -49.5, 0.11278, 43, 10.04, -48.88, 0.88722, 2, 42, 89.09, -50.34, 0.01254, 43, 36.12, -47.72, 0.98746, 4, 42, 43.78, 71.86, 0.39023, 43, -18.38, 70.66, 0.21525, 31, 31.46, -93.8, 0.26395, 32, -37.41, -90.57, 0.13057, 4, 42, 51.64, 23.66, 0.61303, 43, -6.87, 23.2, 0.32344, 31, 19.83, -141.23, 0.04021, 32, -53.62, -136.64, 0.02332, 4, 42, 35.27, 119.95, 0.12805, 43, -30.55, 117.97, 0.07757, 31, 42.44, -46.2, 0.55606, 32, -21.82, -44.28, 0.23832 ],
					"hull": 28,
					"edges": [ 0, 2, 2, 4, 4, 6, 6, 8, 12, 14, 14, 16, 16, 18, 18, 20, 20, 22, 22, 24, 24, 26, 26, 28, 28, 30, 30, 32, 32, 34, 38, 40, 40, 42, 42, 44, 44, 46, 46, 48, 48, 50, 50, 52, 52, 54, 0, 54, 8, 10, 10, 12, 34, 36, 36, 38 ],
					"width": 473,
					"height": 253
				}
			},
			"yifuwai2": {
				"yifudi": { "x": 64.19, "y": -11.94, "rotation": -88.97, "width": 473, "height": 253 }
			},
			"yifuwai4": {
				"yifulinzi": {
					"type": "mesh",
					"uvs": [ 0.02183, 0.27723, 0, 0.32549, 0, 0.3755, 0.04811, 0.37901, 0.09974, 0.40007, 0.15943, 0.42857, 0.21061, 0.46991, 0.25421, 0.52793, 0.28607, 0.5861, 0.25603, 0.66156, 0.28372, 0.73176, 0.30531, 0.79581, 0.3269, 0.85548, 0.39355, 0.85723, 0.46536, 0.85987, 0.53576, 0.86513, 0.59302, 0.86601, 0.60178, 0.76334, 0.63276, 0.71333, 0.66327, 0.66068, 0.62009, 0.58171, 0.64825, 0.51678, 0.69631, 0.44919, 0.74979, 0.41113, 0.80174, 0.38048, 0.85987, 0.35657, 0.92483, 0.33627, 1, 0.32201, 1, 0.25511, 0.96711, 0.16202, 0.91366, 0.09649, 0.83921, 0.03822, 0.75732, 0.0115, 0.68164, 0, 0.6043, 0, 0.53966, 0, 0.44789, 0, 0.35785, 0.01125, 0.28764, 0.03499, 0.22677, 0.06784, 0.16542, 0.11095, 0.11329, 0.15769, 0.06344, 0.2138, 0.45602, 0.65709, 0.36497, 0.38887, 0.56969, 0.40331 ],
					"triangles": [ 13, 12, 11, 11, 10, 43, 10, 9, 8, 8, 44, 43, 8, 7, 44, 7, 6, 44, 10, 8, 43, 20, 45, 21, 21, 45, 22, 18, 17, 20, 18, 20, 19, 16, 15, 17, 17, 15, 43, 13, 43, 14, 15, 14, 43, 43, 13, 11, 17, 43, 20, 43, 45, 20, 43, 44, 45, 44, 36, 45, 6, 39, 44, 39, 38, 44, 38, 37, 44, 44, 37, 36, 5, 40, 6, 6, 40, 39, 4, 41, 5, 5, 41, 40, 3, 42, 4, 4, 42, 41, 3, 1, 0, 3, 0, 42, 3, 2, 1, 23, 32, 24, 24, 31, 25, 24, 32, 31, 25, 30, 26, 25, 31, 30, 27, 26, 28, 26, 30, 29, 26, 29, 28, 33, 45, 34, 45, 33, 22, 36, 35, 45, 22, 33, 23, 23, 33, 32, 45, 35, 34 ],
					"vertices": [ 1, 64, 101.7, -0.37, 1, 1, 64, 111.58, 12.2, 1, 1, 64, 111.12, 24.85, 1, 1, 64, 88.35, 24.92, 1, 2, 64, 63.75, 29.37, 0.99629, 42, -1.87, -103.81, 0.00371, 3, 64, 35.28, 35.56, 0.88158, 63, 68.18, 47.81, 0.04944, 42, 0.84, -74.8, 0.06898, 3, 64, 10.71, 45.15, 0.41757, 63, 41.95, 45.01, 0.24504, 42, 7.39, -49.25, 0.33739, 3, 64, -10.42, 59.07, 0.07765, 63, 16.78, 47.64, 0.10561, 42, 18.66, -26.59, 0.81675, 2, 64, -26.01, 73.24, 0.003, 42, 30.84, -9.41, 0.997, 3, 4, 21.25, 102.7, 1.0E-5, 42, 51.92, -20.45, 0.85776, 43, -3.22, -20.76, 0.14223, 2, 42, 67.41, -4.74, 0.02982, 43, 11.03, -3.91, 0.97018, 3, 4, -12.3, 78.78, 0.09383, 42, 81.82, 7.88, 0.0012, 43, 24.43, 9.77, 0.90497, 2, 4, -27.21, 68.3, 0.20265, 43, 36.76, 23.2, 0.79735, 3, 4, -27.08, 36.77, 0.54384, 42, 90.65, 51.53, 0.01976, 43, 29.9, 53.97, 0.43641, 4, 4, -27.14, 2.8, 0.92236, 31, 75.52, -98.05, 0.01494, 42, 86, 85.18, 2.8E-4, 43, 22.69, 87.17, 0.06242, 2, 4, -27.87, -30.52, 0.80463, 31, 84.89, -66.07, 0.19537, 2, 4, -27.61, -57.6, 0.66944, 31, 91.67, -39.85, 0.33056, 2, 4, -1.56, -61.28, 0.46832, 31, 67.48, -29.53, 0.53168, 2, 4, 11.35, -75.7, 0.14423, 31, 58.76, -12.24, 0.85577, 1, 31, 49.33, 4.99, 1, 2, 4, 44.54, -69.11, 0.07061, 31, 25, -9.98, 0.92939, 2, 61, -0.94, -35.11, 0.05107, 31, 12.29, 6.93, 0.94893, 3, 61, 26.6, -27.97, 0.74208, 62, -33.59, -38.94, 0.00496, 31, 1.22, 33.13, 0.25295, 3, 61, 53.65, -28.71, 0.7502, 62, -7.41, -32.07, 0.23081, 31, -1.99, 60, 0.01899, 2, 61, 79.33, -30.91, 0.1624, 62, 17.85, -26.99, 0.8376, 2, 61, 107.05, -35.81, 5.5E-4, 62, 45.84, -23.92, 0.99945, 1, 62, 76.94, -22.11, 1, 1, 62, 112.68, -22.33, 1, 1, 62, 114.49, -5.5, 1, 1, 62, 101.55, 19.58, 1, 1, 62, 78.18, 38.77, 1, 3, 61, 128.73, 42.37, 0.05042, 62, 44.75, 57.2, 0.94885, 63, -163.15, -196.38, 7.4E-4, 4, 61, 95.51, 63.39, 0.37461, 62, 6.96, 68.07, 0.60875, 63, -126.1, -183.2, 0.0157, 4, 189.95, -131.42, 9.4E-4, 4, 61, 63.52, 79.73, 0.6949, 62, -28.32, 74.8, 0.22352, 63, -93.51, -168.12, 0.06414, 4, 192.21, -95.57, 0.01745, 4, 61, 29.7, 93.68, 0.72964, 62, -64.69, 78.71, 0.04244, 63, -61.66, -150.12, 0.16255, 4, 191.56, -59, 0.06537, 4, 61, 1.44, 105.34, 0.59831, 62, -95.09, 81.99, 0.00463, 63, -35.04, -135.08, 0.28459, 4, 191.01, -28.42, 0.11246, 4, 61, -38.69, 121.9, 0.36573, 64, -97.18, -77.69, 0.00388, 63, 2.75, -113.72, 0.50086, 4, 190.22, 14.98, 0.12953, 4, 61, -79.14, 135.51, 0.18286, 64, -54.73, -73.32, 0.06443, 63, 38.42, -90.28, 0.67572, 4, 186.61, 57.51, 0.07699, 4, 61, -112.13, 142.62, 0.08104, 64, -21.75, -66.13, 0.26021, 63, 64.38, -68.72, 0.63149, 4, 180.01, 90.6, 0.02727, 4, 61, -141.92, 145.91, 0.02572, 64, 6.72, -56.79, 0.62634, 63, 85.36, -47.31, 0.34392, 4, 171.18, 119.24, 0.00402, 3, 61, -172.9, 146.9, 0.00303, 64, 35.33, -44.85, 0.9482, 63, 105.25, -23.54, 0.04877, 1, 64, 59.55, -32.15, 1, 1, 64, 82.6, -17.11, 1, 3, 4, 24.08, 8.14, 0.95135, 42, 36.01, 72.8, 0.03393, 43, -26.2, 71, 0.01472, 4, 61, -112.46, 45.9, 0.01979, 63, -11.52, -8.77, 0.788, 4, 91.15, 52.42, 0.13332, 42, -24.28, 19.65, 0.05889, 4, 61, -24.34, 5.6, 0.52444, 63, -97.61, -53.24, 0.02776, 4, 89.24, -44.46, 0.25201, 31, -24.57, -22.16, 0.19579 ],
					"hull": 43,
					"edges": [ 0, 2, 2, 4, 4, 6, 6, 8, 8, 10, 10, 12, 12, 14, 14, 16, 16, 18, 18, 20, 20, 22, 22, 24, 24, 26, 26, 28, 28, 30, 30, 32, 32, 34, 34, 36, 36, 38, 38, 40, 40, 42, 42, 44, 44, 46, 46, 48, 48, 50, 50, 52, 52, 54, 54, 56, 56, 58, 58, 60, 60, 62, 62, 64, 64, 66, 66, 68, 68, 70, 70, 72, 72, 74, 74, 76, 76, 78, 78, 80, 80, 82, 82, 84, 0, 84 ],
					"width": 473,
					"height": 253
				}
			},
			"yifuwai7": {
				"yifuxiuzi": {
					"type": "mesh",
					"uvs": [ 0.06295, 0.45247, 0.02131, 0.55067, 0.07769, 0.6345, 0.14046, 0.68361, 0.21285, 0.71115, 0.29357, 0.72552, 0.37876, 0.73271, 0.46909, 0.73391, 0.55749, 0.73031, 0.66511, 0.72193, 0.74582, 0.70277, 0.82244, 0.68121, 0.89611, 0.6369, 0.95505, 0.57582, 0.9922, 0.50277, 0.94223, 0.40576, 0.88138, 0.31474, 0.81476, 0.26324, 0.75903, 0.24288, 0.67319, 0.25366, 0.57902, 0.25605, 0.46563, 0.25845, 0.3665, 0.24064, 0.27938, 0.23705, 0.1993, 0.23705, 0.1519, 0.29932, 0.10578, 0.37118 ],
					"triangles": [ 9, 19, 10, 10, 19, 18, 22, 5, 23, 5, 4, 23, 8, 7, 21, 8, 20, 9, 8, 21, 20, 9, 20, 19, 21, 7, 6, 21, 6, 22, 6, 5, 22, 4, 26, 25, 3, 0, 26, 4, 3, 26, 1, 0, 2, 3, 2, 0, 4, 25, 23, 23, 25, 24, 10, 17, 11, 11, 16, 12, 11, 17, 16, 12, 15, 13, 12, 16, 15, 13, 15, 14, 10, 18, 17 ],
					"vertices": [ 3, 67, 94.22, -26.59, 0.21471, 68, 46.23, -23.37, 0.78308, 4, 72.5, 194.96, 0.00221, 3, 67, 121.96, -11.23, 0.12395, 68, 72.81, -6.08, 0.8668, 4, 47.3, 214.21, 0.00925, 3, 67, 105.5, 18.61, 0.1271, 68, 54.28, 22.51, 0.83268, 4, 26.57, 187.17, 0.04023, 3, 67, 82.87, 41.5, 0.18755, 68, 30.08, 43.74, 0.69284, 4, 14.69, 157.25, 0.11962, 3, 67, 53.94, 61.1, 0.23962, 68, -0.16, 61.24, 0.49111, 4, 8.33, 122.89, 0.26927, 3, 67, 20.1, 79.14, 0.23636, 68, -35.2, 76.84, 0.28892, 4, 5.38, 84.66, 0.47472, 1, 4, 4.29, 44.33, 1, 1, 4, 4.76, 1.61, 1, 1, 4, 6.42, -40.18, 1, 5, 65, 15.44, -86.64, 0.11486, 66, -45.16, -81.8, 0.24272, 67, -142.47, 145.89, 0.00704, 68, -202.09, 131.9, 0.0014, 4, 9.45, -91.04, 0.63399, 3, 65, 48.52, -66.98, 0.14366, 66, -9.95, -66.26, 0.44287, 4, 14.99, -129.12, 0.41347, 3, 65, 79.59, -47.53, 0.13084, 66, 23.23, -50.69, 0.65688, 4, 21.09, -165.26, 0.21229, 3, 65, 107.08, -23.37, 0.09271, 66, 53.43, -30.01, 0.82771, 4, 32.93, -199.9, 0.07957, 3, 65, 126.49, 1.92, 0.06597, 66, 75.74, -7.24, 0.91376, 4, 48.88, -227.49, 0.02028, 3, 65, 135.24, 25.87, 0.09895, 66, 87.31, 15.49, 0.89873, 4, 67.68, -244.73, 0.00232, 3, 65, 103.79, 38.96, 0.21386, 66, 57.65, 32.27, 0.78472, 4, 91.79, -220.66, 0.00142, 3, 65, 68.21, 48.61, 0.38662, 66, 23.49, 46.12, 0.59623, 4, 114.3, -191.46, 0.01715, 3, 65, 34.12, 48.01, 0.54531, 66, -10.43, 49.62, 0.38095, 4, 126.76, -159.72, 0.07374, 3, 65, 7.88, 42.22, 0.59897, 66, -37.16, 47.03, 0.19663, 4, 131.43, -133.27, 0.2044, 4, 65, -28.27, 23.54, 0.3165, 66, -75.3, 32.84, 0.04723, 67, -191.56, 38, 0.00713, 4, 127.98, -92.73, 0.62914, 1, 4, 126.57, -48.2, 1, 1, 4, 125, 5.41, 1, 5, 65, -162.63, -31.24, 8.7E-4, 66, -215.27, -5.4, 0, 67, -58.93, -20.83, 0.0053, 68, -106.94, -28.49, 4.1E-4, 4, 128.66, 52.37, 0.99341, 4, 65, -200.79, -46.83, 0.01114, 67, -21.24, -37.52, 0.51601, 68, -68.16, -42.46, 0.08808, 4, 128.83, 93.59, 0.38477, 3, 67, 13.72, -52.09, 0.59147, 68, -32.26, -54.51, 0.21223, 4, 128.15, 131.46, 0.1963, 3, 67, 40.48, -46.17, 0.53352, 68, -5.99, -46.71, 0.39781, 4, 111.99, 153.59, 0.06868, 3, 67, 67.61, -37.78, 0.37614, 68, 20.48, -36.42, 0.60862, 4, 93.42, 175.08, 0.01525 ],
					"hull": 27,
					"edges": [ 0, 2, 2, 4, 4, 6, 6, 8, 8, 10, 10, 12, 12, 14, 14, 16, 16, 18, 18, 20, 20, 22, 22, 24, 24, 26, 26, 28, 28, 30, 30, 32, 32, 34, 34, 36, 36, 38, 38, 40, 40, 42, 42, 44, 44, 46, 46, 48, 48, 50, 50, 52, 0, 52 ],
					"width": 473,
					"height": 253
				}
			}
		}
	}
],
"animations": {
	"Idle": {
		"bones": {
			"shadow": {
				"scale": [
					{ "x": 0.6 }
				]
			},
			"Body": {
				"translate": [
					{ "curve": 0.25, "c3": 0.75 },
					{ "time": 1, "y": -1.81, "curve": 0.25, "c3": 0.75 },
					{ "time": 2 }
				]
			},
			"Rf_ctrl": {
				"translate": [
					{}
				]
			},
			"Lh": {
				"translate": [
					{ "curve": 0.25, "c3": 0.75 },
					{ "time": 1, "x": -15.31, "curve": 0.25, "c3": 0.75 },
					{ "time": 2 }
				]
			},
			"Lh_1": {
				"rotate": [
					{ "angle": -23.07, "curve": 0.25, "c3": 0.75 },
					{ "time": 1, "angle": 2.56, "curve": 0.25, "c3": 0.75 },
					{ "time": 2, "angle": -23.07 }
				]
			},
			"Lh_2": {
				"rotate": [
					{ "angle": 33.4, "curve": 0.25, "c3": 0.75 },
					{ "time": 1, "angle": 3.93, "curve": 0.25, "c3": 0.75 },
					{ "time": 2, "angle": 33.4 }
				]
			},
			"Head": {
				"translate": [
					{ "curve": "stepped" },
					{ "time": 2 }
				]
			},
			"headctrl": {
				"translate": [
					{ "curve": 0.25, "c3": 0.75 },
					{ "time": 1, "x": -28.21, "curve": 0.25, "c3": 0.75 },
					{ "time": 2 }
				]
			},
			"Rh": {
				"translate": [
					{ "curve": 0.25, "c3": 0.75 },
					{ "time": 1, "x": -12.92, "curve": 0.25, "c3": 0.75 },
					{ "time": 2 }
				]
			},
			"Rh_1": {
				"rotate": [
					{ "angle": -23.31, "curve": 0.25, "c3": 0.75 },
					{ "time": 1, "angle": -5.05, "curve": 0.25, "c3": 0.75 },
					{ "time": 2, "angle": -23.31 }
				]
			},
			"Rh_2": {
				"rotate": [
					{ "angle": 33.09, "curve": 0.25, "c3": 0.75 },
					{ "time": 1, "angle": 8.02, "curve": 0.25, "c3": 0.75 },
					{ "time": 2, "angle": 33.09 }
				]
			},
			"Hat6": {
				"rotate": [
					{ "angle": 0.2, "curve": 0.36, "c2": 0.64, "c3": 0.695 },
					{ "time": 0.1, "curve": 0.25, "c3": 0.75 },
					{ "time": 1.1, "angle": 4.75, "curve": 0.245, "c3": 0.711, "c4": 0.83 },
					{ "time": 2, "angle": 0.2 }
				]
			},
			"Hat8": {
				"rotate": [
					{ "angle": 1.15, "curve": 0.382, "c2": 0.58, "c3": 0.731 },
					{ "time": 0.3, "curve": 0.25, "c3": 0.75 },
					{ "time": 1.3, "angle": 4.75, "curve": 0.243, "c3": 0.655, "c4": 0.63 },
					{ "time": 2, "angle": 1.15 }
				]
			},
			"Hat7": {
				"rotate": [
					{ "angle": 0.62, "curve": 0.375, "c2": 0.62, "c3": 0.716 },
					{ "time": 0.2, "curve": 0.25, "c3": 0.75 },
					{ "time": 1.2, "angle": 4.75, "curve": 0.243, "c3": 0.68, "c4": 0.71 },
					{ "time": 2, "angle": 0.62 }
				]
			},
			"Hat4": {
				"rotate": [
					{ "angle": -0.34, "curve": 0.371, "c2": 0.62, "c3": 0.71 },
					{ "time": 0.1667, "curve": 0.25, "c3": 0.75 },
					{ "time": 1.1667, "angle": -3.53, "curve": 0.243, "c3": 0.689, "c4": 0.75 },
					{ "time": 2, "angle": -0.34 }
				]
			},
			"Hat5": {
				"rotate": [
					{ "angle": -1, "curve": 0.382, "c2": 0.57, "c3": 0.735 },
					{ "time": 0.3333, "curve": 0.25, "c3": 0.75 },
					{ "time": 1.3333, "angle": -3.53, "curve": 0.243, "c3": 0.649, "c4": 0.6 },
					{ "time": 2, "angle": -1 }
				]
			},
			"Hat1": {
				"rotate": [
					{ "angle": -1.36, "curve": 0.371, "c2": 0.62, "c3": 0.71 },
					{ "time": 0.1667, "angle": -1.78, "curve": 0.25, "c3": 0.75 },
					{ "time": 1.1667, "angle": 2.6, "curve": 0.243, "c3": 0.689, "c4": 0.75 },
					{ "time": 2, "angle": -1.36 }
				]
			},
			"Hat3": {
				"rotate": [
					{ "angle": 0.41, "curve": 0.375, "c2": 0.5, "c3": 0.75 },
					{ "time": 0.5, "angle": -1.78, "curve": 0.25, "c3": 0.75 },
					{ "time": 1.5, "angle": 2.6, "curve": 0.25, "c3": 0.625, "c4": 0.5 },
					{ "time": 2, "angle": 0.41 }
				]
			},
			"Hat2": {
				"rotate": [
					{ "angle": -0.54, "curve": 0.382, "c2": 0.57, "c3": 0.735 },
					{ "time": 0.3333, "angle": -1.78, "curve": 0.25, "c3": 0.75 },
					{ "time": 1.3333, "angle": 2.6, "curve": 0.243, "c3": 0.649, "c4": 0.6 },
					{ "time": 2, "angle": -0.54 }
				]
			},
			"hz1": {
				"rotate": [
					{ "angle": -4.55, "curve": 0.352, "c2": 0.65, "c3": 0.687 },
					{ "time": 0.0667, "angle": -4.71, "curve": 0.25, "c3": 0.75 },
					{ "time": 1.0667, "angle": 2.69, "curve": 0.246, "c3": 0.723, "c4": 0.88 },
					{ "time": 2, "angle": -4.55 }
				]
			},
			"hz3": {
				"rotate": [
					{ "angle": -3.75, "curve": 0.375, "c2": 0.62, "c3": 0.716 },
					{ "time": 0.2, "angle": -4.71, "curve": 0.25, "c3": 0.75 },
					{ "time": 1.2, "angle": 2.69, "curve": 0.243, "c3": 0.68, "c4": 0.71 },
					{ "time": 2, "angle": -3.75 }
				]
			},
			"hz2": {
				"rotate": [
					{ "angle": -4.2, "curve": 0.366, "c2": 0.63, "c3": 0.703 },
					{ "time": 0.1333, "angle": -4.71, "curve": 0.25, "c3": 0.75 },
					{ "time": 1.1333, "angle": 2.69, "curve": 0.244, "c3": 0.7, "c4": 0.79 },
					{ "time": 2, "angle": -4.2 }
				]
			},
			"hz4": {
				"rotate": [
					{ "angle": 5.78, "curve": 0.352, "c2": 0.65, "c3": 0.687 },
					{ "time": 0.0667, "angle": 5.96, "curve": 0.25, "c3": 0.75 },
					{ "time": 1.0667, "angle": -1.82, "curve": 0.246, "c3": 0.723, "c4": 0.88 },
					{ "time": 2, "angle": 5.78 }
				]
			},
			"hz6": {
				"rotate": [
					{ "angle": 4.95, "curve": 0.375, "c2": 0.62, "c3": 0.716 },
					{ "time": 0.2, "angle": 5.96, "curve": 0.25, "c3": 0.75 },
					{ "time": 1.2, "angle": -1.82, "curve": 0.243, "c3": 0.68, "c4": 0.71 },
					{ "time": 2, "angle": 4.95 }
				]
			},
			"hz5": {
				"rotate": [
					{ "angle": 5.42, "curve": 0.366, "c2": 0.63, "c3": 0.703 },
					{ "time": 0.1333, "angle": 5.96, "curve": 0.25, "c3": 0.75 },
					{ "time": 1.1333, "angle": -1.82, "curve": 0.244, "c3": 0.7, "c4": 0.79 },
					{ "time": 2, "angle": 5.42 }
				]
			},
			"Hat9": {
				"rotate": [
					{ "angle": 11.19, "curve": 0.25, "c3": 0.75 },
					{ "time": 1, "angle": -2.61, "curve": 0.25, "c3": 0.75 },
					{ "time": 2, "angle": 11.19 }
				]
			},
			"Hat10": {
				"rotate": [
					{ "angle": -8.48, "curve": 0.25, "c3": 0.75 },
					{ "time": 1, "angle": 1.84, "curve": 0.25, "c3": 0.75 },
					{ "time": 2, "angle": -8.48 }
				]
			},
			"Lh_qt4": {
				"rotate": [
					{ "curve": 0.25, "c3": 0.75 },
					{ "time": 1, "angle": -12.34, "curve": 0.25, "c3": 0.75 },
					{ "time": 2 }
				]
			},
			"Lh_qt5": {
				"rotate": [
					{ "curve": 0.25, "c3": 0.75 },
					{ "time": 1, "angle": -12.34, "curve": 0.25, "c3": 0.75 },
					{ "time": 2 }
				]
			},
			"Lh_qt": {
				"rotate": [
					{ "curve": 0.25, "c3": 0.75 },
					{ "time": 1, "angle": 7.13, "curve": 0.25, "c3": 0.75 },
					{ "time": 2 }
				]
			},
			"Lh_qt2": {
				"rotate": [
					{ "curve": 0.25, "c3": 0.75 },
					{ "time": 1, "angle": 7.13, "curve": 0.25, "c3": 0.75 },
					{ "time": 2 }
				]
			},
			"Lh_qt3": {
				"rotate": [
					{ "curve": 0.25, "c3": 0.75 },
					{ "time": 1, "angle": 7.13, "curve": 0.25, "c3": 0.75 },
					{ "time": 2 }
				]
			},
			"Rh_qt4": {
				"rotate": [
					{ "curve": 0.25, "c3": 0.75 },
					{ "time": 1, "angle": -10.78, "curve": 0.25, "c3": 0.75 },
					{ "time": 2 }
				]
			},
			"Rh_qt5": {
				"rotate": [
					{ "curve": 0.25, "c3": 0.75 },
					{ "time": 1, "angle": -10.78, "curve": 0.25, "c3": 0.75 },
					{ "time": 2 }
				]
			},
			"Rh_3": {
				"rotate": [
					{ "curve": 0.25, "c3": 0.75 },
					{ "time": 1, "angle": 7.74, "curve": 0.25, "c3": 0.75 },
					{ "time": 2 }
				]
			},
			"Rh_qt3": {
				"rotate": [
					{ "curve": 0.25, "c3": 0.75 },
					{ "time": 1, "angle": 7.74, "curve": 0.25, "c3": 0.75 },
					{ "time": 2 }
				]
			},
			"Rh_qt2": {
				"rotate": [
					{ "curve": 0.25, "c3": 0.75 },
					{ "time": 1, "angle": 7.74, "curve": 0.25, "c3": 0.75 },
					{ "time": 2 }
				]
			},
			"yandou": {
				"translate": [
					{ "curve": 0.25, "c3": 0.75 },
					{ "time": 1, "x": -10.4, "y": -2.21, "curve": 0.25, "c3": 0.75 },
					{ "time": 2 }
				]
			},
			"yanjing": {
				"translate": [
					{ "curve": 0.25, "c3": 0.75 },
					{ "time": 1, "x": -2.8, "y": -5.2, "curve": 0.25, "c3": 0.75 },
					{ "time": 2 }
				]
			},
			"Body3": {
				"rotate": [
					{ "curve": 0.25, "c3": 0.75 },
					{ "time": 1, "angle": -5.21, "curve": 0.25, "c3": 0.75 },
					{ "time": 2 }
				]
			},
			"Body4": {
				"rotate": [
					{ "angle": -1.48, "curve": 0.382, "c2": 0.57, "c3": 0.735 },
					{ "time": 0.3333, "curve": 0.25, "c3": 0.75 },
					{ "time": 1.3333, "angle": -5.21, "curve": 0.243, "c3": 0.649, "c4": 0.6 },
					{ "time": 2, "angle": -1.48 }
				]
			},
			"Body5": {
				"rotate": [
					{ "curve": 0.25, "c3": 0.75 },
					{ "time": 1, "angle": 4.73, "curve": 0.25, "c3": 0.75 },
					{ "time": 2 }
				]
			},
			"Body6": {
				"rotate": [
					{ "angle": 1.34, "curve": 0.382, "c2": 0.57, "c3": 0.735 },
					{ "time": 0.3333, "curve": 0.25, "c3": 0.75 },
					{ "time": 1.3333, "angle": 4.73, "curve": 0.243, "c3": 0.649, "c4": 0.6 },
					{ "time": 2, "angle": 1.34 }
				]
			},
			"Body9": {
				"rotate": [
					{},
					{ "time": 1, "angle": -4.25 },
					{ "time": 2 }
				]
			},
			"Body10": {
				"rotate": [
					{},
					{ "time": 1, "angle": -4.25 },
					{ "time": 2 }
				]
			},
			"Body7": {
				"rotate": [
					{ "curve": 0.25, "c3": 0.75 },
					{ "time": 1, "angle": 4.29, "curve": 0.25, "c3": 0.75 },
					{ "time": 2 }
				]
			},
			"Body8": {
				"rotate": [
					{ "curve": 0.25, "c3": 0.75 },
					{ "time": 1, "angle": 4.29, "curve": 0.25, "c3": 0.75 },
					{ "time": 2 }
				]
			},
			"Body13": {
				"rotate": [
					{ "curve": 0.25, "c3": 0.75 },
					{ "time": 1, "angle": -3.64, "curve": 0.25, "c3": 0.75 },
					{ "time": 2 }
				]
			},
			"Body14": {
				"rotate": [
					{ "angle": -0.35, "curve": 0.371, "c2": 0.62, "c3": 0.71 },
					{ "time": 0.1667, "curve": 0.25, "c3": 0.75 },
					{ "time": 1.1667, "angle": -3.64, "curve": 0.243, "c3": 0.689, "c4": 0.75 },
					{ "time": 2, "angle": -0.35 }
				]
			},
			"Body11": {
				"rotate": [
					{ "curve": 0.25, "c3": 0.75 },
					{ "time": 1, "angle": 4.24, "curve": 0.25, "c3": 0.75 },
					{ "time": 2 }
				]
			},
			"Body12": {
				"rotate": [
					{ "angle": 0.41, "curve": 0.371, "c2": 0.62, "c3": 0.71 },
					{ "time": 0.1667, "curve": 0.25, "c3": 0.75 },
					{ "time": 1.1667, "angle": 4.24, "curve": 0.243, "c3": 0.689, "c4": 0.75 },
					{ "time": 2, "angle": 0.41 }
				]
			}
		}
	}
}
}