{
"skeleton": {
	"hash": "OoDowg2QVddvNJPCzKk/DmXqx/I",
	"spine": "3.8.99",
	"x": -28.01,
	"y": -2.8,
	"width": 178,
	"height": 78,
	"images": "",
	"audio": ""
},
"bones": [
	{ "name": "root" },
	{ "name": "tips", "parent": "root" }
],
"slots": [
	{ "name": "image/qipao", "bone": "tips", "attachment": "image/lxgf" }
],
"skins": [
	{
		"name": "default",
		"attachments": {
			"image/qipao": {
				"image/lxgf": { "x": 60.99, "y": 36.2, "width": 178, "height": 78 }
			}
		}
	}
],
"animations": {
	"animation": {
		"bones": {
			"tips": {
				"rotate": [
					{ "angle": 3, "curve": 0.25, "c3": 0.75 },
					{ "time": 0.3333, "angle": -3, "curve": 0.25, "c3": 0.75 },
					{ "time": 0.6667, "angle": 3 }
				],
				"translate": [
					{ "x": 9.5, "y": 6.41 }
				]
			}
		}
	}
}
}